[
  {
    "_id": {
      "$oid": "69c7e23b41bebaf5f1978aff"
    },
    "id": "c1683c8c-f237-4861-b1cb-c178b8748a35",
    "date": "2026-03-17",
    "account": "cash",
    "txn_type": "nikasi",
    "amount": 1225.0,
    "category": "Hemali Payment",
    "party_type": "Hemali",
    "description": "Hemali: Rajesh - Paddy Unload x200.0, Gummy Load x250.0",
    "reference": "hemali_payment:3ca6fc2c-5890-44dc-9033-755b8457dba5",
    "kms_year": "2025-2026",
    "season": "",
    "created_by": "admin",
    "created_at": "2026-03-17T08:24:57.836838+00:00",
    "updated_at": "2026-03-17T08:24:57.836838+00:00"
  },
  {
    "_id": {
      "$oid": "69c7e23b41bebaf5f1978b00"
    },
    "id": "ce236cd3-092a-49c4-a62e-7625300d9c54",
    "date": "2026-03-17",
    "account": "ledger",
    "txn_type": "jama",
    "amount": 1225.0,
    "category": "Hemali Payment",
    "party_type": "Hemali",
    "description": "Rajesh - Paddy Unload x200.0, Gummy Load x250.0 | Total: Rs.1225",
    "reference": "hemali_work:3ca6fc2c-5890-44dc-9033-755b8457dba5",
    "kms_year": "2025-2026",
    "season": "",
    "created_by": "admin",
    "created_at": "2026-03-17T08:24:57.836838+00:00",
    "updated_at": "2026-03-17T08:24:57.836838+00:00"
  },
  {
    "_id": {
      "$oid": "69c7e23b41bebaf5f1978b01"
    },
    "id": "d3ccd1fe-a6a0-40bb-b330-f5d16ac736a0",
    "date": "2026-03-17",
    "account": "ledger",
    "txn_type": "nikasi",
    "amount": 1225.0,
    "category": "Hemali Payment",
    "party_type": "Hemali",
    "description": "Rajesh - Paid Rs.1225",
    "reference": "hemali_paid:3ca6fc2c-5890-44dc-9033-755b8457dba5",
    "kms_year": "2025-2026",
    "season": "",
    "created_by": "admin",
    "created_at": "2026-03-17T08:24:57.836838+00:00",
    "updated_at": "2026-03-17T08:24:57.836838+00:00"
  },
  {
    "_id": {
      "$oid": "69c7e23b41bebaf5f1978b02"
    },
    "id": "908af3cd-3659-464f-9af0-0dd91f39dbe0",
    "date": "2026-03-22",
    "account": "cash",
    "txn_type": "nikasi",
    "category": "OD19F2002",
    "party_type": "Truck",
    "description": "Truck Payment: OD19F2002 - Rs.11968.0",
    "amount": 11968.0,
    "reference": "truck_pay:34f64d6a",
    "kms_year": "2025-2026",
    "season": "Kharif",
    "created_by": "admin",
    "linked_payment_id": "truck:34f64d6a-9f7f-447b-8996-f206ae6a8fc0",
    "created_at": "2026-03-22T18:10:15.659878+00:00",
    "updated_at": "2026-03-22T18:10:15.659882+00:00"
  },
  {
    "_id": {
      "$oid": "69c7e23b41bebaf5f1978b03"
    },
    "id": "c3610e1d-8096-4bf2-a50b-207a135f44b2",
    "date": "2026-03-22",
    "account": "ledger",
    "txn_type": "nikasi",
    "category": "OD19F2002",
    "party_type": "Truck",
    "description": "Truck Payment: OD19F2002 - Rs.11968.0",
    "amount": 11968.0,
    "reference": "truck_pay_ledger:34f64d6a",
    "kms_year": "2025-2026",
    "season": "Kharif",
    "created_by": "admin",
    "linked_payment_id": "truck_ledger:34f64d6a-9f7f-447b-8996-f206ae6a8fc0:8a852c",
    "created_at": "2026-03-22T18:10:15.660415+00:00",
    "updated_at": "2026-03-22T18:10:15.660418+00:00"
  },
  {
    "_id": {
      "$oid": "69c7e23b41bebaf5f1978b07"
    },
    "id": "2e2e5825-239e-4b52-9fbb-90974b03ad0b",
    "date": "2026-03-23",
    "account": "ledger",
    "txn_type": "jama",
    "category": "Test Party",
    "party_type": "Local Party",
    "description": "Mill Part: Test Pipe x5.0 @ Rs.100.0 - Test Party",
    "amount": 500.0,
    "reference": "lp_mill_part:3f1ab6a0",
    "kms_year": "2025-2026",
    "season": "All",
    "created_by": "",
    "linked_local_party_id": "15d9d23d-cce8-472d-bdcb-b47d2b01fc5d",
    "created_at": "2026-03-23T10:17:06.736446+00:00",
    "updated_at": "2026-03-23T10:17:06.736451+00:00"
  },
  {
    "_id": {
      "$oid": "69c7e23b41bebaf5f1978b08"
    },
    "id": "03742599-150d-48d2-b61b-4ca4ed36b0b4",
    "date": "2026-03-23",
    "account": "ledger",
    "txn_type": "jama",
    "category": "Test Vendor",
    "party_type": "Local Party",
    "description": "Purchase: Test Vendor - Test purchase Rs.5000.0",
    "amount": 5000.0,
    "reference": "lp_purchase:845bd880",
    "kms_year": "2025-2026",
    "season": "All",
    "created_by": "admin",
    "linked_local_party_id": "845bd880-f68b-4b21-9a41-7a43408339e4",
    "created_at": "2026-03-23T11:05:01.234942+00:00",
    "updated_at": "2026-03-23T11:05:01.234948+00:00"
  },
  {
    "_id": {
      "$oid": "69c7e23b41bebaf5f1978b09"
    },
    "id": "2819fcbb-2eb9-42bb-a72b-0598dfaaa957",
    "date": "2026-03-23",
    "account": "ledger",
    "txn_type": "jama",
    "category": "TestParty",
    "party_type": "Local Party",
    "description": "Purchase: TestParty - Test purchase Rs.2000.0",
    "amount": 2000.0,
    "reference": "lp_purchase:3a41db4c",
    "kms_year": "2025-2026",
    "season": "All",
    "created_by": "admin",
    "linked_local_party_id": "3a41db4c-25ec-4a12-8d59-fe2752b10a38",
    "created_at": "2026-03-23T16:28:41.492386+00:00",
    "updated_at": "2026-03-23T16:28:41.492391+00:00"
  },
  {
    "_id": {
      "$oid": "69c7e23b41bebaf5f1978b0a"
    },
    "id": "b14fbba1-0b43-4b55-a277-99efd8f4c98e",
    "date": "2026-03-23",
    "account": "cash",
    "txn_type": "nikasi",
    "category": "TestPump",
    "party_type": "Diesel",
    "description": "Diesel Payment: TestPump - Rs.4500.0",
    "amount": 4500.0,
    "reference": "diesel_pay:67327fac",
    "kms_year": "2025-2026",
    "season": "All",
    "created_by": "system",
    "linked_diesel_payment_id": "67327fac-ca3d-4578-bb2e-72e6b703b510",
    "created_at": "2026-03-23T17:07:22.700685+00:00",
    "updated_at": "2026-03-23T17:07:22.700694+00:00"
  },
  {
    "_id": {
      "$oid": "69c7e23b41bebaf5f1978b0b"
    },
    "id": "3731b431-759c-4d8c-b31f-9e3d97b5fde7",
    "date": "2026-03-23",
    "account": "ledger",
    "txn_type": "nikasi",
    "category": "TestPump",
    "party_type": "Diesel",
    "description": "Diesel Payment: TestPump - Rs.5000.0 (Cash: 4500.0, Round Off: 500.0)",
    "amount": 5000.0,
    "reference": "diesel_pay_ledger:67327fac",
    "kms_year": "2025-2026",
    "season": "All",
    "created_by": "system",
    "linked_diesel_payment_id": "67327fac-ca3d-4578-bb2e-72e6b703b510",
    "created_at": "2026-03-23T17:07:22.701314+00:00",
    "updated_at": "2026-03-23T17:07:22.701317+00:00"
  },
  {
    "_id": {
      "$oid": "69c7e23b41bebaf5f1978b0c"
    },
    "id": "44cbe314-4951-4e13-9bf2-2c85817cf1a3",
    "date": "2026-03-23",
    "account": "ledger",
    "txn_type": "jama",
    "category": "RO_Test",
    "party_type": "Local Party",
    "description": "Purchase: RO_Test - Test Rs.10000.0",
    "amount": 10000.0,
    "reference": "lp_purchase:e79bdcbf",
    "kms_year": "2025-2026",
    "season": "All",
    "created_by": "admin",
    "linked_local_party_id": "e79bdcbf-6d68-4f1f-928a-e20109f8386b",
    "created_at": "2026-03-23T17:08:02.869710+00:00",
    "updated_at": "2026-03-23T17:08:02.869717+00:00"
  },
  {
    "_id": {
      "$oid": "69c7e23b41bebaf5f1978b0d"
    },
    "id": "f53c6b26-9c95-448e-a8be-d76ce3637b19",
    "date": "2026-03-23",
    "account": "ledger",
    "txn_type": "jama",
    "category": "TestLP",
    "party_type": "Local Party",
    "description": "Purchase: TestLP - Bill Rs.10000.0",
    "amount": 10000.0,
    "reference": "lp_purchase:1c24dfb1",
    "kms_year": "2025-2026",
    "season": "All",
    "created_by": "admin",
    "linked_local_party_id": "1c24dfb1-50c5-47ac-8b8a-46c083c811be",
    "created_at": "2026-03-23T17:10:11.552735+00:00",
    "updated_at": "2026-03-23T17:10:11.552739+00:00"
  },
  {
    "_id": {
      "$oid": "69c7e23b41bebaf5f1978b0e"
    },
    "id": "ba647823-b1f2-4bb3-aa0b-a15f438b9935",
    "date": "2026-03-23",
    "account": "cash",
    "txn_type": "nikasi",
    "category": "Jain",
    "party_type": "Diesel",
    "description": "Cash payment to Jain",
    "amount": 2000.0,
    "reference": "",
    "bank_name": "",
    "kms_year": "2025-2026",
    "season": "Kharif",
    "created_by": "admin",
    "created_at": "2026-03-23T17:25:42.479105+00:00",
    "updated_at": "2026-03-23T17:25:42.479118+00:00"
  },
  {
    "_id": {
      "$oid": "69c7e23b41bebaf5f1978b0f"
    },
    "id": "2433a4aa-a005-4b6e-93e1-49c31a01847a",
    "date": "2026-03-23",
    "account": "ledger",
    "txn_type": "nikasi",
    "category": "Jain",
    "party_type": "Diesel",
    "description": "Cash payment to Jain",
    "amount": 2500.0,
    "reference": "auto_ledger:ba647823",
    "bank_name": "",
    "kms_year": "2025-2026",
    "season": "Kharif",
    "created_by": "admin",
    "created_at": "2026-03-23T17:25:42.480079+00:00",
    "updated_at": "2026-03-24T10:56:02.573849+00:00",
    "updated_by": ""
  },
  {
    "_id": {
      "$oid": "69c7e23b41bebaf5f1978b10"
    },
    "id": "5a5e09df-ec7a-41fe-b05f-c4301e8fa229",
    "date": "2026-03-23",
    "account": "cash",
    "txn_type": "nikasi",
    "category": "OD19E4567",
    "party_type": "Truck",
    "description": "Cash payment to OD19E4567",
    "amount": 9532.0,
    "reference": "",
    "bank_name": "",
    "kms_year": "2025-2026",
    "season": "All",
    "created_by": "",
    "created_at": "2026-03-23T17:26:49.915947+00:00",
    "updated_at": "2026-03-23T17:26:49.915960+00:00"
  },
  {
    "_id": {
      "$oid": "69c7e23b41bebaf5f1978b11"
    },
    "id": "0ec9f9aa-f104-48d7-b1d0-84be072f3f75",
    "date": "2026-03-23",
    "account": "ledger",
    "txn_type": "nikasi",
    "category": "OD19E4567",
    "party_type": "Truck",
    "description": "Cash payment to OD19E4567",
    "amount": 10000.0,
    "reference": "auto_ledger:5a5e09df",
    "bank_name": "",
    "kms_year": "2025-2026",
    "season": "All",
    "created_by": "",
    "created_at": "2026-03-23T17:26:49.916859+00:00",
    "updated_at": "2026-03-24T10:56:00.390459+00:00",
    "updated_by": ""
  },
  {
    "_id": {
      "$oid": "69c7e23b41bebaf5f1978b12"
    },
    "id": "e7df765c-7868-4a3c-861c-9d75e2e3994d",
    "date": "2026-03-24",
    "account": "cash",
    "txn_type": "jama",
    "category": "Titu",
    "party_type": "Cash Party",
    "description": "Titu se liya",
    "amount": 50000.0,
    "reference": "",
    "bank_name": "",
    "kms_year": "2025-2026",
    "season": "Kharif",
    "created_by": "admin",
    "created_at": "2026-03-24T11:41:22.969118+00:00",
    "updated_at": "2026-03-24T11:41:22.969128+00:00"
  },
  {
    "_id": {
      "$oid": "69c7e23b41bebaf5f1978b14"
    },
    "id": "e610a601-945c-4e4d-837a-e75a9df5a368",
    "date": "2026-03-24",
    "account": "cash",
    "txn_type": "jama",
    "category": "Titu",
    "party_type": "Cash Party",
    "description": "Titu se liya",
    "amount": 30000.0,
    "reference": "",
    "bank_name": "",
    "kms_year": "2025-2026",
    "season": "Kharif",
    "created_by": "admin",
    "created_at": "2026-03-24T11:41:23.118053+00:00",
    "updated_at": "2026-03-24T11:41:23.118065+00:00"
  },
  {
    "_id": {
      "$oid": "69c7e23b41bebaf5f1978b16"
    },
    "id": "fae52336-3f8e-4589-9fb4-a36a3ed202df",
    "date": "2026-03-24",
    "account": "cash",
    "txn_type": "nikasi",
    "category": "Titu",
    "party_type": "Cash Party",
    "description": "Titu ko diya",
    "amount": 10000.0,
    "reference": "",
    "bank_name": "",
    "kms_year": "2025-2026",
    "season": "Kharif",
    "created_by": "admin",
    "created_at": "2026-03-24T11:41:23.230008+00:00",
    "updated_at": "2026-03-24T11:41:23.230019+00:00"
  },
  {
    "_id": {
      "$oid": "69c7e23b41bebaf5f1978b18"
    },
    "id": "0f220246-385e-40f2-bf04-9c39171465c1",
    "date": "2026-03-25",
    "account": "cash",
    "txn_type": "jama",
    "category": "TestPartyA",
    "party_type": "Cash Party",
    "description": "Test cash received",
    "amount": 15000.0,
    "reference": "",
    "bank_name": "",
    "kms_year": "2025-2026",
    "season": "kharif",
    "created_by": "",
    "created_at": "2026-03-25T09:30:11.665640+00:00",
    "updated_at": "2026-03-25T18:44:25.416365+00:00",
    "updated_by": "admin"
  },
  {
    "_id": {
      "$oid": "69c7e23b41bebaf5f1978b19"
    },
    "id": "b0cb436c-03c2-40c2-9c9e-87a96cc816a6",
    "date": "2026-03-25",
    "account": "ledger",
    "txn_type": "jama",
    "category": "TestPartyA",
    "party_type": "Cash Party",
    "description": "Test cash received",
    "amount": 15000.0,
    "reference": "auto_ledger:0f220246",
    "bank_name": "",
    "kms_year": "2025-2026",
    "season": "kharif",
    "created_by": "",
    "created_at": "2026-03-25T09:30:11.665640+00:00",
    "updated_at": "2026-03-25T18:44:25.416365+00:00",
    "updated_by": "admin"
  },
  {
    "_id": {
      "$oid": "69c7e23b41bebaf5f1978b1a"
    },
    "id": "a3a113a0-5042-4798-ab43-74a26ec18483",
    "date": "2026-03-25",
    "account": "cash",
    "txn_type": "nikasi",
    "category": "MH-12-AB-1234",
    "party_type": "Truck",
    "description": "Cash Paid: Truck MH-12-AB-1234 - Mandi TestMandi - Rs.2000.0",
    "amount": 2000.0,
    "reference": "entry_cash:9362f0d5",
    "kms_year": "2025-2026",
    "season": "kharif",
    "created_by": "system",
    "linked_entry_id": "9362f0d5-8a47-4728-826d-a82d6a6ad3ac",
    "created_at": "2026-03-25T09:30:52.078063+00:00",
    "updated_at": "2026-03-25T18:44:25.095296+00:00",
    "updated_by": "admin"
  },
  {
    "_id": {
      "$oid": "69c7e23b41bebaf5f1978b1b"
    },
    "id": "8416e709-13bf-4c0d-b21f-45e68b64401a",
    "date": "2026-03-25",
    "account": "ledger",
    "txn_type": "nikasi",
    "category": "MH-12-AB-1234",
    "party_type": "Truck",
    "description": "Truck Cash Advance: MH-12-AB-1234 - Rs.2000.0",
    "amount": 2000.0,
    "reference": "truck_cash_ded:9362f0d5",
    "kms_year": "2025-2026",
    "season": "kharif",
    "created_by": "system",
    "linked_entry_id": "9362f0d5-8a47-4728-826d-a82d6a6ad3ac",
    "created_at": "2026-03-25T09:30:52.078431+00:00",
    "updated_at": "2026-03-25T18:44:24.944378+00:00",
    "updated_by": "admin"
  },
  {
    "_id": {
      "$oid": "69c7e23b41bebaf5f1978b1c"
    },
    "id": "ffdd93c6-433e-40a7-8b12-7433a8e4c68e",
    "date": "2026-03-25",
    "account": "ledger",
    "txn_type": "jama",
    "category": "Jain",
    "party_type": "Diesel",
    "description": "Diesel Fill: Truck MH-12-AB-1234 - Jain - Rs.500.0",
    "amount": 500.0,
    "reference": "diesel_fill:9362f0d5",
    "kms_year": "2025-2026",
    "season": "kharif",
    "created_by": "system",
    "linked_entry_id": "9362f0d5-8a47-4728-826d-a82d6a6ad3ac",
    "created_at": "2026-03-25T09:30:52.081702+00:00",
    "updated_at": "2026-03-25T18:44:24.837253+00:00",
    "updated_by": "admin"
  },
  {
    "_id": {
      "$oid": "69c7e23b41bebaf5f1978b1d"
    },
    "id": "e8901a56-6338-4924-afbc-5f9ed7e7e12f",
    "date": "2026-03-25",
    "account": "bank",
    "txn_type": "jama",
    "category": "MSP Payment",
    "party_type": "MSP",
    "description": "MSP Payment: 20.0Q @ Rs.2300.0/Q",
    "amount": 46000.0,
    "bank_name": "SBI",
    "reference": "msp:40070985",
    "kms_year": "2025-2026",
    "season": "kharif",
    "created_by": "system",
    "linked_payment_id": "msp:40070985-b861-4d19-ac93-4f16349bd085",
    "created_at": "2026-03-25T09:30:52.438793+00:00",
    "updated_at": "2026-03-25T18:44:24.724429+00:00",
    "updated_by": "admin"
  },
  {
    "_id": {
      "$oid": "69c7e23b41bebaf5f1978b1e"
    },
    "id": "4b7194d6-bed6-428b-8ffb-2b969ac29db3",
    "account": "cash",
    "txn_type": "nikasi",
    "category": "TestFarmer - LocalMandi",
    "party_type": "Pvt Paddy Purchase",
    "description": "TestFarmer - LocalMandi - Rs.10000.0",
    "amount": 10000.0,
    "reference": "pvt_pay:4d91b654",
    "date": "2026-03-25",
    "kms_year": "2025-2026",
    "season": "kharif",
    "created_by": "",
    "linked_payment_id": "4d91b654-a5bf-4993-b074-b246bf1365ee",
    "created_at": "2026-03-25T09:31:06.219043+00:00",
    "updated_at": "2026-03-25T18:44:24.436400+00:00",
    "updated_by": "admin"
  },
  {
    "_id": {
      "$oid": "69c7e23b41bebaf5f1978b1f"
    },
    "id": "e6e2c884-d9aa-4abd-9acd-5d48cff08021",
    "account": "ledger",
    "txn_type": "nikasi",
    "category": "TestFarmer - LocalMandi",
    "party_type": "Pvt Paddy Purchase",
    "description": "TestFarmer - LocalMandi - Rs.10000.0",
    "amount": 10000.0,
    "reference": "pvt_pay_ledger:4d91b654",
    "date": "2026-03-25",
    "kms_year": "2025-2026",
    "season": "kharif",
    "created_by": "",
    "linked_payment_id": "4d91b654-a5bf-4993-b074-b246bf1365ee",
    "created_at": "2026-03-25T09:31:06.219043+00:00",
    "updated_at": "2026-03-25T18:44:24.566796+00:00",
    "updated_by": "admin"
  },
  {
    "_id": {
      "$oid": "69c7e23b41bebaf5f1978b20"
    },
    "id": "6b0db830-2e88-4804-9afb-0510f297c2ea",
    "date": "2026-03-25",
    "account": "ledger",
    "txn_type": "jama",
    "category": "TestBuyer",
    "party_type": "Rice Sale",
    "description": "Rice Sale: TestBuyer - 30 Qntl @ Rs.3200",
    "amount": 96000.0,
    "reference": "rice_sale_jama:a341aee0",
    "kms_year": "2025-2026",
    "season": "kharif",
    "created_by": "system",
    "linked_entry_id": "a341aee0-5fdc-42b9-aaad-eaa78299663a",
    "created_at": "2026-03-25T09:31:06.323580+00:00",
    "updated_at": "2026-03-25T18:44:24.307894+00:00",
    "updated_by": "admin"
  },
  {
    "_id": {
      "$oid": "69c7e23b41bebaf5f1978b21"
    },
    "id": "0238d8f8-277d-4006-83f5-c840551acf00",
    "date": "2026-03-25",
    "account": "ledger",
    "txn_type": "jama",
    "amount": 35000,
    "category": "TestSaleBuyer",
    "party_type": "Sale Book",
    "description": "Sale #1 - Raw Rice",
    "reference": "sale_voucher:3ee7b398-0c56-4e4e-a151-00285d1cefe1",
    "kms_year": "2025-2026",
    "season": "",
    "created_by": "",
    "created_at": "2026-03-25T09:31:06.433447+00:00",
    "updated_at": "2026-04-26T13:42:59.780086+00:00",
    "updated_by": "admin"
  },
  {
    "_id": {
      "$oid": "69c7e23b41bebaf5f1978b22"
    },
    "id": "faad2a2d-32e4-4397-b262-858956c1121c",
    "date": "2026-03-25",
    "account": "ledger",
    "txn_type": "jama",
    "amount": 5000,
    "category": "TestSeller",
    "party_type": "Purchase Voucher",
    "description": "Purchase #1 - Gunny Bags",
    "reference": "purchase_voucher:e5a62d62-d132-4b82-b90d-462a67003099",
    "kms_year": "2025-2026",
    "season": "",
    "created_by": "",
    "created_at": "2026-03-25T09:31:06.541882+00:00",
    "updated_at": "2026-04-26T13:42:59.780086+00:00",
    "updated_by": "admin"
  },
  {
    "_id": {
      "$oid": "69c7e23b41bebaf5f1978b23"
    },
    "id": "9d61f534-afbe-4a10-abf9-6d5ac5c9c1af",
    "date": "2026-03-25",
    "account": "ledger",
    "txn_type": "jama",
    "amount": 2500.0,
    "category": "Government Supply",
    "party_type": "Gunny Bag",
    "description": "Gunny Bags x100 @ Rs.25.0",
    "reference": "gunny_purchase:e7b79ac7-17b4-45e3-8338-a38a831be65b",
    "kms_year": "2025-2026",
    "season": "kharif",
    "created_by": "",
    "created_at": "2026-03-25T09:31:23.730618+00:00",
    "updated_at": "2026-03-25T18:44:23.928083+00:00",
    "updated_by": "admin"
  },
  {
    "_id": {
      "$oid": "69c7e23b41bebaf5f1978b24"
    },
    "id": "ee6832f3-652a-4557-a340-37a41a6eb210",
    "date": "2026-03-25",
    "account": "ledger",
    "txn_type": "jama",
    "amount": 16000.0,
    "category": "TestByProductBuyer",
    "party_type": "By-Product Sale",
    "description": "Husk sale - 20.0 Qntl @ Rs.800.0/Q",
    "reference": "byproduct:f1b13ba4-53e5-4b74-a13b-41dbd5ab3254",
    "kms_year": "2025-2026",
    "season": "kharif",
    "created_by": "",
    "created_at": "2026-03-25T09:31:24.051897+00:00",
    "updated_at": "2026-03-25T18:44:23.789629+00:00",
    "updated_by": "admin"
  },
  {
    "_id": {
      "$oid": "69c7e23b41bebaf5f1978b25"
    },
    "id": "23e1f6b7-502a-4c15-91d0-bc3312078539",
    "date": "2026-03-25",
    "account": "cash",
    "txn_type": "jama",
    "amount": 15000.0,
    "category": "TestSaleBuyer",
    "party_type": "Sale Book",
    "description": "Payment received - Sale #1 - TestSaleBuyer",
    "reference": "voucher_payment:2cd121ff-0c0a-4556-b572-32f209992943",
    "kms_year": "2025-2026",
    "season": "",
    "created_by": "system",
    "created_at": "2026-03-25T09:35:56.373738+00:00",
    "updated_at": "2026-03-25T18:44:23.553636+00:00",
    "updated_by": "admin"
  },
  {
    "_id": {
      "$oid": "69c7e23b41bebaf5f1978b26"
    },
    "id": "00cad2f5-2041-4977-9939-2fd5c3e6d29e",
    "date": "2026-03-25",
    "account": "ledger",
    "txn_type": "nikasi",
    "amount": 15000.0,
    "category": "TestSaleBuyer",
    "party_type": "Sale Book",
    "description": "Payment received - Sale #1 - TestSaleBuyer - Rs.15000.0",
    "reference": "voucher_payment_ledger:2cd121ff-0c0a-4556-b572-32f209992943",
    "kms_year": "2025-2026",
    "season": "",
    "created_by": "system",
    "created_at": "2026-03-25T09:35:56.373738+00:00",
    "updated_at": "2026-03-25T18:44:23.681103+00:00",
    "updated_by": "admin"
  },
  {
    "_id": {
      "$oid": "69c7e23b41bebaf5f1978b28"
    },
    "id": "bcf6cb6d-38ac-48da-9fd0-6e7e8ab79470",
    "date": "2026-03-22",
    "account": "ledger",
    "txn_type": "nikasi",
    "category": "OD19F2002",
    "party_type": "Truck",
    "description": "Truck Diesel Advance: OD19F2002 - Rs.2500.0",
    "amount": 2500.0,
    "reference": "truck_diesel_ded:34f64d6a",
    "kms_year": "2025-2026",
    "season": "Kharif",
    "created_by": "admin",
    "linked_entry_id": "34f64d6a-9f7f-447b-8996-f206ae6a8fc0",
    "created_at": "2026-03-25T18:41:02.723813+00:00",
    "updated_at": "2026-03-25T18:41:02.723816+00:00"
  },
  {
    "_id": {
      "$oid": "69c7e23b41bebaf5f1978b29"
    },
    "id": "a8539043-a92e-41e6-9a70-d211cb499531",
    "date": "2026-03-22",
    "account": "cash",
    "txn_type": "nikasi",
    "category": "OD19F2002",
    "party_type": "Truck",
    "description": "Cash Paid: Truck OD19F2002 - Mandi Kesinga - Rs.1500.0",
    "amount": 1500.0,
    "reference": "entry_cash:34f64d6a",
    "kms_year": "2025-2026",
    "season": "Kharif",
    "created_by": "admin",
    "linked_entry_id": "34f64d6a-9f7f-447b-8996-f206ae6a8fc0",
    "created_at": "2026-03-25T18:41:02.724355+00:00",
    "updated_at": "2026-03-25T18:41:02.724359+00:00"
  },
  {
    "_id": {
      "$oid": "69c7e23b41bebaf5f1978b2a"
    },
    "id": "34fa2df3-3411-43f5-82ee-635f71494e1d",
    "date": "2026-03-22",
    "account": "ledger",
    "txn_type": "nikasi",
    "category": "OD19F2002",
    "party_type": "Truck",
    "description": "Truck Cash Advance: OD19F2002 - Rs.1500.0",
    "amount": 1500.0,
    "reference": "truck_cash_ded:34f64d6a",
    "kms_year": "2025-2026",
    "season": "Kharif",
    "created_by": "admin",
    "linked_entry_id": "34f64d6a-9f7f-447b-8996-f206ae6a8fc0",
    "created_at": "2026-03-25T18:41:02.724805+00:00",
    "updated_at": "2026-03-25T18:41:02.724809+00:00"
  },
  {
    "_id": {
      "$oid": "69c7e23b41bebaf5f1978b2b"
    },
    "id": "404b87be-9051-4d8b-bccb-f73e55fc0c02",
    "date": "2026-03-22",
    "account": "ledger",
    "txn_type": "jama",
    "category": "Jain",
    "party_type": "Diesel",
    "description": "Diesel Fill: Truck OD19F2002 - Jain - Rs.2500.0",
    "amount": 2500.0,
    "reference": "diesel_fill:34f64d6a",
    "kms_year": "2025-2026",
    "season": "Kharif",
    "created_by": "admin",
    "linked_entry_id": "34f64d6a-9f7f-447b-8996-f206ae6a8fc0",
    "created_at": "2026-03-25T18:41:02.734196+00:00",
    "updated_at": "2026-03-25T18:41:02.734199+00:00"
  },
  {
    "_id": {
      "$oid": "69c7e23b41bebaf5f1978b2c"
    },
    "id": "f53f3697-ac43-4f15-86ab-8e455a74a183",
    "date": "2026-03-25",
    "account": "ledger",
    "txn_type": "jama",
    "category": "Jaga (Kesinga)",
    "party_type": "Pvt Paddy Purchase",
    "description": "Paddy Purchase: Jaga (Kesinga) - 42.94Q @ Rs.1800.0/Q = Rs.77292.0",
    "amount": 77292.0,
    "bank_name": "",
    "reference": "pvt_party_jama:434b3d40",
    "kms_year": "2025-2026",
    "season": "Kharif",
    "created_by": "admin",
    "linked_entry_id": "434b3d40-0b02-417b-82ae-6fdc790bf9e0",
    "created_at": "2026-03-25T18:44:25.643250+00:00",
    "updated_at": "2026-03-25T18:44:25.643255+00:00"
  },
  {
    "_id": {
      "$oid": "69c7e23b41bebaf5f1978b2d"
    },
    "id": "76e5f9b0-157e-41fb-8ac0-4c946cb9811a",
    "date": "2026-03-25",
    "account": "ledger",
    "txn_type": "jama",
    "category": "OD19F2002",
    "party_type": "Truck",
    "description": "Pvt Paddy Truck: OD19F2002 - Jaga (Kesinga) - 42.94Q @ Rs.32",
    "amount": 1374.08,
    "bank_name": "",
    "reference": "pvt_truck_jama:434b3d40",
    "kms_year": "2025-2026",
    "season": "Kharif",
    "created_by": "admin",
    "linked_entry_id": "434b3d40-0b02-417b-82ae-6fdc790bf9e0",
    "created_at": "2026-03-25T18:44:25.643250+00:00",
    "updated_at": "2026-03-25T18:44:25.643255+00:00"
  },
  {
    "_id": {
      "$oid": "69c7e23b41bebaf5f1978b2e"
    },
    "id": "3654ac1b-b2ed-4462-8114-6c14b584b3d2",
    "date": "2026-03-25",
    "account": "cash",
    "txn_type": "nikasi",
    "category": "TestFarmer",
    "party_type": "Pvt Paddy Purchase",
    "description": "Advance - TestFarmer - Rs.10000.0",
    "amount": 10000.0,
    "reference": "pvt_paddy_adv:1a1ffbec",
    "kms_year": "2025-2026",
    "season": "kharif",
    "created_by": "admin",
    "linked_entry_id": "1a1ffbec-d411-4028-b9b9-78f87ba90888",
    "created_at": "2026-03-25T18:44:25.816512+00:00",
    "updated_at": "2026-03-25T18:44:25.816515+00:00"
  },
  {
    "_id": {
      "$oid": "69c7e23b41bebaf5f1978b2f"
    },
    "id": "f4faa4ae-0083-4b8d-b323-a4d597c4e24a",
    "date": "2026-03-25",
    "account": "ledger",
    "txn_type": "nikasi",
    "category": "TestFarmer",
    "party_type": "Pvt Paddy Purchase",
    "description": "Advance - TestFarmer - Rs.10000.0",
    "amount": 10000.0,
    "reference": "pvt_paddy_advl:1a1ffbec",
    "kms_year": "2025-2026",
    "season": "kharif",
    "created_by": "admin",
    "linked_entry_id": "1a1ffbec-d411-4028-b9b9-78f87ba90888",
    "created_at": "2026-03-25T18:44:25.816512+00:00",
    "updated_at": "2026-03-25T18:44:25.816515+00:00"
  },
  {
    "_id": {
      "$oid": "69c7e23b41bebaf5f1978b30"
    },
    "id": "73c93d0d-1082-4af7-ac4f-f28e59967b56",
    "date": "2026-03-22",
    "account": "ledger",
    "txn_type": "jama",
    "category": "Gulu (Kesinga)",
    "party_type": "Pvt Paddy Purchase",
    "description": "Paddy Purchase: Gulu (Kesinga) - 31.87Q @ Rs.2000/Q = Rs.63740.0",
    "amount": 63740.0,
    "reference": "pvt_party_jama:8a119192",
    "kms_year": "2025-2026",
    "season": "Kharif",
    "created_by": "admin",
    "linked_entry_id": "8a119192-c5ca-4e22-9a0a-afc0aa7795b3",
    "created_at": "2026-03-25T19:17:03.331021+00:00",
    "updated_at": "2026-03-25T19:17:03.331041+00:00"
  },
  {
    "_id": {
      "$oid": "69c7e23b41bebaf5f1978b31"
    },
    "id": "df37ff26-c5f4-457c-871e-ebdaf5f13532",
    "date": "2026-03-26",
    "account": "cash",
    "txn_type": "jama",
    "category": "CtrlSTestParty",
    "party_type": "Cash Party",
    "description": "Ctrl+S test transaction",
    "amount": 999.0,
    "reference": "",
    "bank_name": "",
    "kms_year": "2025-2026",
    "season": "Kharif",
    "created_by": "admin",
    "created_at": "2026-03-26T07:36:21.460085+00:00",
    "updated_at": "2026-03-26T07:36:21.460090+00:00"
  },
  {
    "_id": {
      "$oid": "69c7e23b41bebaf5f1978b32"
    },
    "id": "228cad9a-a619-43a5-920c-d7d89d362019",
    "date": "2026-03-26",
    "account": "cash",
    "txn_type": "jama",
    "category": "CtrlSTestParty",
    "party_type": "Cash Party",
    "description": "Ctrl+S test transaction",
    "amount": 999.0,
    "reference": "",
    "bank_name": "",
    "kms_year": "2025-2026",
    "season": "Kharif",
    "created_by": "admin",
    "created_at": "2026-03-26T07:36:21.459163+00:00",
    "updated_at": "2026-03-26T07:36:21.459173+00:00"
  },
  {
    "_id": {
      "$oid": "69c7e23b41bebaf5f1978b33"
    },
    "id": "4d2141fa-4e1c-4cb5-ab24-c19dfebd4a01",
    "date": "2026-03-26",
    "account": "ledger",
    "txn_type": "jama",
    "category": "CtrlSTestParty",
    "party_type": "Cash Party",
    "description": "Ctrl+S test transaction",
    "amount": 999.0,
    "reference": "auto_ledger:228cad9a",
    "bank_name": "",
    "kms_year": "2025-2026",
    "season": "Kharif",
    "created_by": "admin",
    "created_at": "2026-03-26T07:36:21.480097+00:00",
    "updated_at": "2026-03-26T07:36:21.480105+00:00"
  },
  {
    "_id": {
      "$oid": "69c7e23b41bebaf5f1978b34"
    },
    "id": "dae35caf-dc2f-411b-936d-17862d13383f",
    "date": "2026-03-26",
    "account": "ledger",
    "txn_type": "jama",
    "category": "CtrlSTestParty",
    "party_type": "Cash Party",
    "description": "Ctrl+S test transaction",
    "amount": 999.0,
    "reference": "auto_ledger:df37ff26",
    "bank_name": "",
    "kms_year": "2025-2026",
    "season": "Kharif",
    "created_by": "admin",
    "created_at": "2026-03-26T07:36:21.480152+00:00",
    "updated_at": "2026-03-26T07:36:21.480155+00:00"
  },
  {
    "_id": {
      "$oid": "69c7e23b41bebaf5f1978b35"
    },
    "id": "1f30bd2b-c8ae-4c2b-960b-5828feca8c2f",
    "date": "2026-03-26",
    "account": "cash",
    "txn_type": "jama",
    "category": "TabCtrlSTest",
    "party_type": "Cash Party",
    "description": "Tab+CtrlS Test",
    "amount": 777.0,
    "reference": "",
    "bank_name": "",
    "kms_year": "2025-2026",
    "season": "Kharif",
    "created_by": "admin",
    "created_at": "2026-03-26T07:39:29.695577+00:00",
    "updated_at": "2026-03-26T07:39:29.695588+00:00"
  },
  {
    "_id": {
      "$oid": "69c7e23b41bebaf5f1978b36"
    },
    "id": "1120742b-528f-493b-b108-59387a9edf73",
    "date": "2026-03-26",
    "account": "ledger",
    "txn_type": "jama",
    "category": "TabCtrlSTest",
    "party_type": "Cash Party",
    "description": "Tab+CtrlS Test",
    "amount": 777.0,
    "reference": "auto_ledger:1f30bd2b",
    "bank_name": "",
    "kms_year": "2025-2026",
    "season": "Kharif",
    "created_by": "admin",
    "created_at": "2026-03-26T07:39:29.704283+00:00",
    "updated_at": "2026-03-26T07:39:29.704291+00:00"
  },
  {
    "_id": {
      "$oid": "69c7e23b41bebaf5f1978b37"
    },
    "id": "6c59137f-626b-4772-9b3f-0a23b437be32",
    "account": "cash",
    "txn_type": "nikasi",
    "category": "RoundOffTest - TestM",
    "party_type": "Pvt Paddy Purchase",
    "description": "RoundOffTest - TestM - 50 Qntl @ Rs.2000",
    "amount": 100000.0,
    "reference": "pvt_pay:e39e0bb9",
    "date": "2026-03-26",
    "kms_year": "2025-2026",
    "season": "Kharif",
    "created_by": "admin",
    "linked_payment_id": "e39e0bb9-830a-443d-bbb5-b6d2c637134e",
    "created_at": "2026-03-26T09:32:30.471213+00:00",
    "updated_at": "2026-03-26T09:32:30.471217+00:00"
  },
  {
    "_id": {
      "$oid": "69c7e23b41bebaf5f1978b38"
    },
    "id": "879d0696-228d-414d-8b03-c164db806711",
    "account": "ledger",
    "txn_type": "nikasi",
    "category": "RoundOffTest - TestM",
    "party_type": "Pvt Paddy Purchase",
    "description": "RoundOffTest - TestM - 50 Qntl @ Rs.2000 (Cash: 100000.0, Round Off: 60.0)",
    "amount": 100060.0,
    "reference": "pvt_pay_ledger:e39e0bb9",
    "date": "2026-03-26",
    "kms_year": "2025-2026",
    "season": "Kharif",
    "created_by": "admin",
    "linked_payment_id": "e39e0bb9-830a-443d-bbb5-b6d2c637134e",
    "created_at": "2026-03-26T09:32:30.471213+00:00",
    "updated_at": "2026-03-26T09:32:30.471217+00:00"
  },
  {
    "_id": {
      "$oid": "69c7e23b41bebaf5f1978b39"
    },
    "id": "6fa8089a-3879-4c9a-acfd-e01232f3ceba",
    "account": "cash",
    "txn_type": "nikasi",
    "category": "Kridha (Kesinga)",
    "party_type": "Pvt Paddy Purchase",
    "description": "Kridha (Kesinga) - 50 Qntl @ Rs.1980",
    "amount": 50000.0,
    "reference": "pvt_pay:644ddd18",
    "date": "2026-03-26",
    "kms_year": "2025-2026",
    "season": "Kharif",
    "created_by": "admin",
    "linked_payment_id": "644ddd18-444b-4313-92bd-ff6883920fd7",
    "created_at": "2026-03-26T10:47:35.392780+00:00",
    "updated_at": "2026-03-26T10:47:35.392790+00:00"
  },
  {
    "_id": {
      "$oid": "69c7e23b41bebaf5f1978b3a"
    },
    "id": "3cbbfafe-5a5f-44d6-905b-ebe863c9ddee",
    "account": "ledger",
    "txn_type": "nikasi",
    "category": "Kridha (Kesinga)",
    "party_type": "Pvt Paddy Purchase",
    "description": "Kridha (Kesinga) - 50 Qntl @ Rs.1980",
    "amount": 50000.0,
    "reference": "pvt_pay_ledger:644ddd18",
    "date": "2026-03-26",
    "kms_year": "2025-2026",
    "season": "Kharif",
    "created_by": "admin",
    "linked_payment_id": "644ddd18-444b-4313-92bd-ff6883920fd7",
    "created_at": "2026-03-26T10:47:35.392780+00:00",
    "updated_at": "2026-03-26T10:47:35.392790+00:00"
  },
  {
    "_id": {
      "$oid": "69c7e23b41bebaf5f1978b3b"
    },
    "id": "523c8112-4d8f-4122-b259-48498421df04",
    "account": "cash",
    "txn_type": "nikasi",
    "category": "TEST_MarkPaidParty - MarkPaidMandi",
    "party_type": "Pvt Paddy Purchase",
    "description": "TEST_MarkPaidParty - MarkPaidMandi - 3 Qntl @ Rs.2156 (Mark Paid)",
    "amount": 6468.0,
    "reference": "mark_paid:1d621813",
    "date": "2025-01-15",
    "kms_year": "2024-2025",
    "season": "Kharif",
    "created_by": "admin",
    "linked_payment_id": "mark_paid:1d621813",
    "created_at": "2026-03-27T14:11:53.960544+00:00",
    "updated_at": "2026-03-27T14:11:53.960548+00:00"
  },
  {
    "_id": {
      "$oid": "69c7e23b41bebaf5f1978b3c"
    },
    "id": "c3047940-9f56-4991-a1d1-003392c8ab0e",
    "account": "ledger",
    "txn_type": "nikasi",
    "category": "TEST_MarkPaidParty - MarkPaidMandi",
    "party_type": "Pvt Paddy Purchase",
    "description": "TEST_MarkPaidParty - MarkPaidMandi - 3 Qntl @ Rs.2156 (Mark Paid)",
    "amount": 6468.0,
    "reference": "mark_paid_ledger:1d621813",
    "date": "2025-01-15",
    "kms_year": "2024-2025",
    "season": "Kharif",
    "created_by": "admin",
    "linked_payment_id": "mark_paid:1d621813",
    "created_at": "2026-03-27T14:11:53.960544+00:00",
    "updated_at": "2026-03-27T14:11:53.960548+00:00"
  },
  {
    "_id": {
      "$oid": "69c7e23b41bebaf5f1978b3d"
    },
    "id": "4ee32447-dd67-41ae-a281-b3d6a1ad34c7",
    "account": "cash",
    "txn_type": "nikasi",
    "category": "TEST_MarkPaidHistParty - MarkPaidHistMandi",
    "party_type": "Pvt Paddy Purchase",
    "description": "TEST_MarkPaidHistParty - MarkPaidHistMandi - 5 Qntl @ Rs.1960 (Mark Paid)",
    "amount": 9800.0,
    "reference": "mark_paid:2ba5b98a",
    "date": "2025-01-15",
    "kms_year": "2024-2025",
    "season": "Kharif",
    "created_by": "admin",
    "linked_payment_id": "mark_paid:2ba5b98a",
    "created_at": "2026-03-27T14:11:55.769642+00:00",
    "updated_at": "2026-03-27T14:11:55.769645+00:00"
  },
  {
    "_id": {
      "$oid": "69c7e23b41bebaf5f1978b3e"
    },
    "id": "f7b3b633-efa7-48fe-a0cd-08ff3e40b727",
    "account": "ledger",
    "txn_type": "nikasi",
    "category": "TEST_MarkPaidHistParty - MarkPaidHistMandi",
    "party_type": "Pvt Paddy Purchase",
    "description": "TEST_MarkPaidHistParty - MarkPaidHistMandi - 5 Qntl @ Rs.1960 (Mark Paid)",
    "amount": 9800.0,
    "reference": "mark_paid_ledger:2ba5b98a",
    "date": "2025-01-15",
    "kms_year": "2024-2025",
    "season": "Kharif",
    "created_by": "admin",
    "linked_payment_id": "mark_paid:2ba5b98a",
    "created_at": "2026-03-27T14:11:55.769642+00:00",
    "updated_at": "2026-03-27T14:11:55.769645+00:00"
  },
  {
    "_id": {
      "$oid": "69c7e23b41bebaf5f1978b3f"
    },
    "id": "cdaa5f50-cb43-4ce2-8489-208b175c4b76",
    "date": "2026-03-27",
    "account": "ledger",
    "txn_type": "jama",
    "category": "TEST_UIAdvanceParty - UITestMandi",
    "party_type": "Pvt Paddy Purchase",
    "description": "Paddy Purchase: TEST_UIAdvanceParty - UITestMandi - 4.9Q @ Rs.2000.0/Q = Rs.9800.0",
    "amount": 9800.0,
    "bank_name": "",
    "reference": "pvt_party_jama:f4c7fe22",
    "kms_year": "2025-2026",
    "season": "Kharif",
    "created_by": "admin",
    "linked_entry_id": "f4c7fe22-4554-47ba-85c2-04c3d7f7aff7",
    "created_at": "2026-03-27T14:15:11.222554+00:00",
    "updated_at": "2026-03-27T14:15:11.222556+00:00"
  },
  {
    "_id": {
      "$oid": "69c7e23b41bebaf5f1978b40"
    },
    "id": "ee9205fc-1794-4cf7-8246-e0a8ab924e13",
    "date": "2026-03-27",
    "account": "ledger",
    "txn_type": "jama",
    "category": "OD99XX9999",
    "party_type": "Truck",
    "description": "Pvt Paddy Truck: OD99XX9999 - TEST_UIAdvanceParty - UITestMandi - 4.9Q @ Rs.32",
    "amount": 156.8,
    "bank_name": "",
    "reference": "pvt_truck_jama:f4c7fe22",
    "kms_year": "2025-2026",
    "season": "Kharif",
    "created_by": "admin",
    "linked_entry_id": "f4c7fe22-4554-47ba-85c2-04c3d7f7aff7",
    "created_at": "2026-03-27T14:15:11.222554+00:00",
    "updated_at": "2026-03-27T14:15:11.222556+00:00"
  },
  {
    "_id": {
      "$oid": "69c7e23b41bebaf5f1978b41"
    },
    "id": "3cc78301-9129-4d3b-aa90-60d016f93a95",
    "date": "2026-03-27",
    "account": "cash",
    "txn_type": "nikasi",
    "category": "TEST_UIAdvanceParty - UITestMandi",
    "party_type": "Pvt Paddy Purchase",
    "description": "Advance - 4.9 Qntl @ Rs.2000",
    "amount": 10000.0,
    "reference": "pvt_paddy_adv:f4c7fe22",
    "kms_year": "2025-2026",
    "season": "Kharif",
    "created_by": "admin",
    "linked_entry_id": "f4c7fe22-4554-47ba-85c2-04c3d7f7aff7",
    "created_at": "2026-03-27T14:15:11.222554+00:00",
    "updated_at": "2026-03-27T14:15:11.222556+00:00"
  },
  {
    "_id": {
      "$oid": "69c7e23b41bebaf5f1978b42"
    },
    "id": "859118f0-55ac-4461-98cc-c624e2d40061",
    "date": "2026-03-27",
    "account": "ledger",
    "txn_type": "nikasi",
    "category": "TEST_UIAdvanceParty - UITestMandi",
    "party_type": "Pvt Paddy Purchase",
    "description": "Advance - 4.9 Qntl @ Rs.2000",
    "amount": 10000.0,
    "reference": "pvt_paddy_advl:f4c7fe22",
    "kms_year": "2025-2026",
    "season": "Kharif",
    "created_by": "admin",
    "linked_entry_id": "f4c7fe22-4554-47ba-85c2-04c3d7f7aff7",
    "created_at": "2026-03-27T14:15:11.222554+00:00",
    "updated_at": "2026-03-27T14:15:11.222556+00:00"
  },
  {
    "_id": {
      "$oid": "69c7e23b41bebaf5f1978b43"
    },
    "id": "d591ae7b-775b-4920-9329-759c9ec3c81d",
    "date": "2026-03-27",
    "account": "cash",
    "txn_type": "nikasi",
    "category": "TestFull - TestM",
    "party_type": "Pvt Paddy Purchase",
    "description": "Manual payment",
    "amount": 50000.0,
    "reference": "",
    "bank_name": "",
    "kms_year": "2025-2026",
    "season": "Kharif",
    "created_by": "",
    "created_at": "2026-03-27T16:05:55.737378+00:00",
    "updated_at": "2026-03-27T16:05:55.737389+00:00"
  },
  {
    "_id": {
      "$oid": "69c7e23b41bebaf5f1978b44"
    },
    "id": "0d98c814-a709-4114-a28d-6c12b2a032f8",
    "date": "2026-03-27",
    "account": "ledger",
    "txn_type": "nikasi",
    "category": "TestFull - TestM",
    "party_type": "Pvt Paddy Purchase",
    "description": "Manual payment",
    "amount": 50000.0,
    "reference": "auto_ledger:d591ae7b",
    "bank_name": "",
    "kms_year": "2025-2026",
    "season": "Kharif",
    "created_by": "",
    "created_at": "2026-03-27T16:05:55.738236+00:00",
    "updated_at": "2026-03-27T16:05:55.738241+00:00"
  },
  {
    "_id": {
      "$oid": "69c7e23b41bebaf5f1978b45"
    },
    "id": "34eb8953-64bb-4121-88e6-265a76a05742",
    "date": "2026-03-27",
    "account": "cash",
    "txn_type": "nikasi",
    "category": "Debug1 - DebugM",
    "party_type": "Pvt Paddy Purchase",
    "description": "Manual pay",
    "amount": 30000.0,
    "reference": "",
    "bank_name": "",
    "kms_year": "2025-2026",
    "season": "Kharif",
    "created_by": "",
    "created_at": "2026-03-27T16:06:31.383986+00:00",
    "updated_at": "2026-03-27T16:06:31.383997+00:00"
  },
  {
    "_id": {
      "$oid": "69c7e23b41bebaf5f1978b46"
    },
    "id": "1c09bbb8-d5a1-4f5e-9323-a52528b28294",
    "date": "2026-03-27",
    "account": "ledger",
    "txn_type": "nikasi",
    "category": "Debug1 - DebugM",
    "party_type": "Pvt Paddy Purchase",
    "description": "Manual pay",
    "amount": 30000.0,
    "reference": "auto_ledger:34eb8953",
    "bank_name": "",
    "kms_year": "2025-2026",
    "season": "Kharif",
    "created_by": "",
    "created_at": "2026-03-27T16:06:31.384821+00:00",
    "updated_at": "2026-03-27T16:06:31.384827+00:00"
  },
  {
    "_id": {
      "$oid": "69c7e23b41bebaf5f1978b47"
    },
    "id": "905a277e-a18d-4549-b591-02dc3904737b",
    "date": "2026-03-27",
    "account": "cash",
    "txn_type": "nikasi",
    "category": "Debug2 - DM2",
    "party_type": "Pvt Paddy Purchase",
    "description": "test",
    "amount": 30000.0,
    "reference": "",
    "bank_name": "",
    "kms_year": "2025-2026",
    "season": "Kharif",
    "created_by": "",
    "created_at": "2026-03-27T16:06:57.260600+00:00",
    "updated_at": "2026-03-27T16:06:57.260609+00:00"
  },
  {
    "_id": {
      "$oid": "69c7e23b41bebaf5f1978b48"
    },
    "id": "49be3bdf-c5dd-4ce8-8925-d679fbd18d29",
    "date": "2026-03-27",
    "account": "ledger",
    "txn_type": "nikasi",
    "category": "Debug2 - DM2",
    "party_type": "Pvt Paddy Purchase",
    "description": "test",
    "amount": 30000.0,
    "reference": "auto_ledger:905a277e",
    "bank_name": "",
    "kms_year": "2025-2026",
    "season": "Kharif",
    "created_by": "",
    "created_at": "2026-03-27T16:06:57.261430+00:00",
    "updated_at": "2026-03-27T16:06:57.261435+00:00"
  },
  {
    "_id": {
      "$oid": "69c7e23b41bebaf5f1978b49"
    },
    "id": "276ef5df-8511-4a0b-9956-482284bddec2",
    "date": "2026-03-27",
    "account": "cash",
    "txn_type": "nikasi",
    "category": "HistTest - HM",
    "party_type": "Pvt Paddy Purchase",
    "description": "test",
    "amount": 30000.0,
    "reference": "",
    "bank_name": "",
    "kms_year": "2025-2026",
    "season": "Kharif",
    "created_by": "",
    "created_at": "2026-03-27T16:07:07.702218+00:00",
    "updated_at": "2026-03-27T16:07:07.702230+00:00"
  },
  {
    "_id": {
      "$oid": "69c7e23b41bebaf5f1978b4a"
    },
    "id": "ed4c07d1-0025-4764-b4a5-d394f89b4ecc",
    "date": "2026-03-27",
    "account": "ledger",
    "txn_type": "nikasi",
    "category": "HistTest - HM",
    "party_type": "Pvt Paddy Purchase",
    "description": "test",
    "amount": 30000.0,
    "reference": "auto_ledger:276ef5df",
    "bank_name": "",
    "kms_year": "2025-2026",
    "season": "Kharif",
    "created_by": "",
    "created_at": "2026-03-27T16:07:07.703013+00:00",
    "updated_at": "2026-03-27T16:07:07.703016+00:00"
  },
  {
    "_id": {
      "$oid": "69c7e23b41bebaf5f1978b4b"
    },
    "id": "6ff758d4-ab3e-43b8-ad72-12e6313eb1ed",
    "date": "2026-03-27",
    "account": "cash",
    "txn_type": "nikasi",
    "category": "DBG - DM",
    "party_type": "Pvt Paddy Purchase",
    "description": "test",
    "amount": 30000.0,
    "reference": "",
    "bank_name": "",
    "kms_year": "2025-2026",
    "season": "Kharif",
    "created_by": "",
    "created_at": "2026-03-27T16:07:22.925273+00:00",
    "updated_at": "2026-03-27T16:07:22.925284+00:00"
  },
  {
    "_id": {
      "$oid": "69c7e23b41bebaf5f1978b4c"
    },
    "id": "85d9f966-1129-4246-a418-a64015606760",
    "date": "2026-03-27",
    "account": "ledger",
    "txn_type": "nikasi",
    "category": "DBG - DM",
    "party_type": "Pvt Paddy Purchase",
    "description": "test",
    "amount": 30000.0,
    "reference": "auto_ledger:6ff758d4",
    "bank_name": "",
    "kms_year": "2025-2026",
    "season": "Kharif",
    "created_by": "",
    "created_at": "2026-03-27T16:07:22.926110+00:00",
    "updated_at": "2026-03-27T16:07:22.926118+00:00"
  },
  {
    "_id": {
      "$oid": "69c92cd731e8326a413c9f2a"
    },
    "id": "0a9eb93d-3397-4a53-b0cf-5f678b09cc15",
    "date": "2026-03-29",
    "account": "ledger",
    "txn_type": "nikasi",
    "amount": 5000.0,
    "category": "OD-01-1234",
    "party_type": "Truck",
    "description": "Truck cash deduction - Sale #2 | Inv:GST-001",
    "reference": "sale_truck_cash:dc55851d-1040-4d29-b595-8ab0d3b2d13c",
    "kms_year": "2025-26",
    "season": "Kharif",
    "created_by": "admin",
    "created_at": "2026-03-29T13:44:55.627664+00:00",
    "updated_at": "2026-03-29T13:44:55.627664+00:00"
  },
  {
    "_id": {
      "$oid": "69c92cd731e8326a413c9f2b"
    },
    "id": "bd09a771-7a1d-4d2b-a423-d416d2b64959",
    "date": "2026-03-29",
    "account": "ledger",
    "txn_type": "nikasi",
    "amount": 2000.0,
    "category": "OD-01-1234",
    "party_type": "Truck",
    "description": "Truck diesel deduction - Sale #2 | Inv:GST-001",
    "reference": "sale_truck_diesel:dc55851d-1040-4d29-b595-8ab0d3b2d13c",
    "kms_year": "2025-26",
    "season": "Kharif",
    "created_by": "admin",
    "created_at": "2026-03-29T13:44:55.627664+00:00",
    "updated_at": "2026-03-29T13:44:55.627664+00:00"
  },
  {
    "_id": {
      "$oid": "69c92d7f31e8326a413c9f2f"
    },
    "id": "38de6b8e-df5e-44e4-8e43-5126e7801e7b",
    "date": "2026-03-29",
    "account": "ledger",
    "txn_type": "jama",
    "amount": 262500.0,
    "category": "Rajan",
    "party_type": "Sale Book",
    "description": "Sale #3 - Rice (Raw) | Inv:INV-2021/123",
    "reference": "sale_voucher:2827d469-7907-4cca-9b5a-49e8af594116",
    "kms_year": "2025-2026",
    "season": "Kharif",
    "created_by": "admin",
    "created_at": "2026-03-29T13:47:43.725985+00:00",
    "updated_at": "2026-03-29T13:47:43.725985+00:00"
  },
  {
    "_id": {
      "$oid": "69c92dfc31e8326a413c9f39"
    },
    "id": "1a4c1afb-cad3-466e-9d59-a275df70bbd7",
    "date": "2026-01-15",
    "account": "ledger",
    "txn_type": "nikasi",
    "amount": 1000.0,
    "category": "BR01AB1234",
    "party_type": "Truck",
    "description": "Truck cash deduction - Sale #4 | Inv:TEST-GST-001",
    "reference": "sale_truck_cash:6c9097b3-d921-4cd6-bf99-12548c5526e6",
    "kms_year": "2025-26",
    "season": "Kharif",
    "created_by": "admin",
    "created_at": "2026-03-29T13:49:48.812453+00:00",
    "updated_at": "2026-03-29T13:49:48.812453+00:00"
  },
  {
    "_id": {
      "$oid": "69c92dfc31e8326a413c9f3a"
    },
    "id": "7841f97d-7f0d-4904-aa07-8d40e81a83d0",
    "date": "2026-01-15",
    "account": "ledger",
    "txn_type": "nikasi",
    "amount": 500.0,
    "category": "BR01AB1234",
    "party_type": "Truck",
    "description": "Truck diesel deduction - Sale #4 | Inv:TEST-GST-001",
    "reference": "sale_truck_diesel:6c9097b3-d921-4cd6-bf99-12548c5526e6",
    "kms_year": "2025-26",
    "season": "Kharif",
    "created_by": "admin",
    "created_at": "2026-03-29T13:49:48.812453+00:00",
    "updated_at": "2026-03-29T13:49:48.812453+00:00"
  },
  {
    "_id": {
      "$oid": "69c92e1131e8326a413c9f4a"
    },
    "id": "640b13c2-7dc0-4c31-8f1b-76b46772d866",
    "date": "2026-01-15",
    "account": "ledger",
    "txn_type": "nikasi",
    "amount": 2000.0,
    "category": "BR01AB1234",
    "party_type": "Truck",
    "description": "Truck cash deduction - Sale #4 | Inv:TEST-GST-001-UPD",
    "reference": "sale_truck_cash:6c9097b3-d921-4cd6-bf99-12548c5526e6",
    "kms_year": "2025-26",
    "season": "Kharif",
    "created_by": "admin",
    "created_at": "2026-03-29T13:50:09.709535+00:00",
    "updated_at": "2026-03-29T13:50:09.709535+00:00"
  },
  {
    "_id": {
      "$oid": "69c92e1131e8326a413c9f4b"
    },
    "id": "782c4527-b94a-48b0-b2d2-70d22ec1e16b",
    "date": "2026-01-15",
    "account": "ledger",
    "txn_type": "nikasi",
    "amount": 1000.0,
    "category": "BR01AB1234",
    "party_type": "Truck",
    "description": "Truck diesel deduction - Sale #4 | Inv:TEST-GST-001-UPD",
    "reference": "sale_truck_diesel:6c9097b3-d921-4cd6-bf99-12548c5526e6",
    "kms_year": "2025-26",
    "season": "Kharif",
    "created_by": "admin",
    "created_at": "2026-03-29T13:50:09.709535+00:00",
    "updated_at": "2026-03-29T13:50:09.709535+00:00"
  },
  {
    "_id": {
      "$oid": "69c92e630bf825f0f61f203f"
    },
    "id": "0d42de25-a527-4e0a-aeab-0848c97148ed",
    "date": "2026-01-15",
    "account": "ledger",
    "txn_type": "nikasi",
    "amount": 1000.0,
    "category": "BR01AB1234",
    "party_type": "Truck",
    "description": "Truck cash deduction - Sale #4 | Inv:TEST-CGST-001",
    "reference": "sale_truck_cash:4a4c0268-a251-4034-ba36-e3ec30096696",
    "kms_year": "2025-26",
    "season": "Kharif",
    "created_by": "admin",
    "created_at": "2026-03-29T13:51:31.243568+00:00",
    "updated_at": "2026-03-29T13:51:31.243568+00:00"
  },
  {
    "_id": {
      "$oid": "69c92e630bf825f0f61f2040"
    },
    "id": "aa6fbf75-da9e-4e22-b9bf-6989851bad36",
    "date": "2026-01-15",
    "account": "ledger",
    "txn_type": "nikasi",
    "amount": 500.0,
    "category": "BR01AB1234",
    "party_type": "Truck",
    "description": "Truck diesel deduction - Sale #4 | Inv:TEST-CGST-001",
    "reference": "sale_truck_diesel:4a4c0268-a251-4034-ba36-e3ec30096696",
    "kms_year": "2025-26",
    "season": "Kharif",
    "created_by": "admin",
    "created_at": "2026-03-29T13:51:31.243568+00:00",
    "updated_at": "2026-03-29T13:51:31.243568+00:00"
  },
  {
    "_id": {
      "$oid": "69c92e640bf825f0f61f205f"
    },
    "id": "0bf44ed7-5628-4ac7-8b94-06b00e2a0c10",
    "date": "2026-01-22",
    "account": "ledger",
    "txn_type": "nikasi",
    "amount": 5000.0,
    "category": "BR01XY9999",
    "party_type": "Truck",
    "description": "Truck cash deduction - Sale #10 | Inv:TEST-DED-001",
    "reference": "sale_truck_cash:04406309-3a9c-457c-baa1-6d6bb517287c",
    "kms_year": "2025-26",
    "season": "Kharif",
    "created_by": "admin",
    "created_at": "2026-03-29T13:51:32.053968+00:00",
    "updated_at": "2026-03-29T13:51:32.053968+00:00"
  },
  {
    "_id": {
      "$oid": "69c92e640bf825f0f61f2060"
    },
    "id": "5779ef44-2702-45fc-8914-e9c8dfb81cfc",
    "date": "2026-01-22",
    "account": "ledger",
    "txn_type": "nikasi",
    "amount": 3000.0,
    "category": "BR01XY9999",
    "party_type": "Truck",
    "description": "Truck diesel deduction - Sale #10 | Inv:TEST-DED-001",
    "reference": "sale_truck_diesel:04406309-3a9c-457c-baa1-6d6bb517287c",
    "kms_year": "2025-26",
    "season": "Kharif",
    "created_by": "admin",
    "created_at": "2026-03-29T13:51:32.053968+00:00",
    "updated_at": "2026-03-29T13:51:32.053968+00:00"
  },
  {
    "_id": {
      "$oid": "69cae13f662a7152c2ea8bb3"
    },
    "id": "b45311da-f0cc-4cdd-8cc9-b4e72603315c",
    "date": "2026-03-30",
    "account": "ledger",
    "txn_type": "nikasi",
    "category": "MP 09 XY 4444",
    "party_type": "Truck",
    "description": "Truck Diesel Advance: MP 09 XY 4444 - Rs.1800.0",
    "amount": 1800.0,
    "reference": "truck_diesel_ded:dd5417a5",
    "kms_year": "2025-2026",
    "season": "Kharif",
    "created_by": "admin",
    "linked_entry_id": "dd5417a5-12dd-4453-9359-8d92294b9533",
    "created_at": "2026-03-30T20:46:55.809244+00:00",
    "updated_at": "2026-03-30T20:46:55.809247+00:00"
  },
  {
    "_id": {
      "$oid": "69cae13f662a7152c2ea8bb4"
    },
    "id": "15989b51-1d23-4ab0-b29f-9bf89a5e275e",
    "date": "2026-03-30",
    "account": "cash",
    "txn_type": "nikasi",
    "category": "MP 09 XY 4444",
    "party_type": "Truck",
    "description": "Cash Paid: Truck MP 09 XY 4444 - Mandi Kesinga - Rs.4000.0",
    "amount": 4000.0,
    "reference": "entry_cash:dd5417a5",
    "kms_year": "2025-2026",
    "season": "Kharif",
    "created_by": "admin",
    "linked_entry_id": "dd5417a5-12dd-4453-9359-8d92294b9533",
    "created_at": "2026-03-30T20:46:55.809644+00:00",
    "updated_at": "2026-03-30T20:46:55.809648+00:00"
  },
  {
    "_id": {
      "$oid": "69cae13f662a7152c2ea8bb5"
    },
    "id": "6c2cc9fa-153e-493b-93b7-bd428a53ccac",
    "date": "2026-03-30",
    "account": "ledger",
    "txn_type": "nikasi",
    "category": "MP 09 XY 4444",
    "party_type": "Truck",
    "description": "Truck Cash Advance: MP 09 XY 4444 - Rs.4000.0",
    "amount": 4000.0,
    "reference": "truck_cash_ded:dd5417a5",
    "kms_year": "2025-2026",
    "season": "Kharif",
    "created_by": "admin",
    "linked_entry_id": "dd5417a5-12dd-4453-9359-8d92294b9533",
    "created_at": "2026-03-30T20:46:55.810057+00:00",
    "updated_at": "2026-03-30T20:46:55.810060+00:00"
  },
  {
    "_id": {
      "$oid": "69cae13f662a7152c2ea8bb7"
    },
    "id": "8b89fee4-cda8-4faa-a0cc-d90bc1af2b98",
    "date": "2026-03-30",
    "account": "ledger",
    "txn_type": "jama",
    "category": "Jain",
    "party_type": "Diesel",
    "description": "Diesel Fill: Truck MP 09 XY 4444 - Jain - Rs.1800.0",
    "amount": 1800.0,
    "reference": "diesel_fill:dd5417a5",
    "kms_year": "2025-2026",
    "season": "Kharif",
    "created_by": "admin",
    "linked_entry_id": "dd5417a5-12dd-4453-9359-8d92294b9533",
    "created_at": "2026-03-30T20:46:55.815968+00:00",
    "updated_at": "2026-03-30T20:46:55.815971+00:00"
  },
  {
    "_id": {
      "$oid": "69ce53a776786c5c90cf924e"
    },
    "id": "badd6510-23eb-4962-9c79-0bef5bb2f6c1",
    "date": "2026-01-15",
    "account": "ledger",
    "txn_type": "jama",
    "category": "TEST_CashEntry_157aa17b - TestMandi",
    "party_type": "Pvt Paddy Purchase",
    "description": "Paddy Purchase: TEST_CashEntry_157aa17b - TestMandi - 9.9Q @ Rs.2000.0/Q = Rs.19800.0",
    "amount": 19800.0,
    "bank_name": "",
    "reference": "pvt_party_jama:6788eb13",
    "kms_year": "2025-2026",
    "season": "Kharif",
    "created_by": "test",
    "linked_entry_id": "6788eb13-5a4b-4b58-b048-652a8ad76b31",
    "created_at": "2026-04-02T11:31:51.768724+00:00",
    "updated_at": "2026-04-02T11:31:51.768728+00:00"
  },
  {
    "_id": {
      "$oid": "69ce53a776786c5c90cf924f"
    },
    "id": "53d4e110-7e39-4eac-afe2-f3ddc686a74b",
    "date": "2026-01-15",
    "account": "ledger",
    "txn_type": "jama",
    "category": "TESTCASH",
    "party_type": "Truck",
    "description": "Pvt Paddy Truck: TESTCASH - TEST_CashEntry_157aa17b - TestMandi - 9.9Q @ Rs.32",
    "amount": 316.8,
    "bank_name": "",
    "reference": "pvt_truck_jama:6788eb13",
    "kms_year": "2025-2026",
    "season": "Kharif",
    "created_by": "test",
    "linked_entry_id": "6788eb13-5a4b-4b58-b048-652a8ad76b31",
    "created_at": "2026-04-02T11:31:51.768724+00:00",
    "updated_at": "2026-04-02T11:31:51.768728+00:00"
  },
  {
    "_id": {
      "$oid": "69ce53a776786c5c90cf9250"
    },
    "id": "a0a912c5-dd06-4e8c-ac01-5e5f5db61ad1",
    "date": "2026-01-15",
    "account": "cash",
    "txn_type": "nikasi",
    "category": "TESTCASH",
    "party_type": "Truck",
    "description": "TEST_CashEntry_157aa17b - TestMandi - 9.9 Qntl @ Rs.2000",
    "amount": 500.0,
    "reference": "pvt_paddy_cash:6788eb13",
    "kms_year": "2025-2026",
    "season": "Kharif",
    "created_by": "test",
    "linked_entry_id": "6788eb13-5a4b-4b58-b048-652a8ad76b31",
    "created_at": "2026-04-02T11:31:51.768724+00:00",
    "updated_at": "2026-04-02T11:31:51.768728+00:00"
  },
  {
    "_id": {
      "$oid": "69ce53a776786c5c90cf9251"
    },
    "id": "9a09818c-6dad-4153-be56-4d327e488cdf",
    "date": "2026-01-15",
    "account": "ledger",
    "txn_type": "nikasi",
    "category": "TESTCASH",
    "party_type": "Truck",
    "description": "TEST_CashEntry_157aa17b - TestMandi - 9.9 Qntl @ Rs.2000",
    "amount": 500.0,
    "reference": "pvt_paddy_tcash:6788eb13",
    "kms_year": "2025-2026",
    "season": "Kharif",
    "created_by": "test",
    "linked_entry_id": "6788eb13-5a4b-4b58-b048-652a8ad76b31",
    "created_at": "2026-04-02T11:31:51.768724+00:00",
    "updated_at": "2026-04-02T11:31:51.768728+00:00"
  },
  {
    "_id": {
      "$oid": "69ce53a776786c5c90cf9253"
    },
    "id": "f6aa37fb-2940-4462-9113-d1277e2383b3",
    "date": "2026-01-15",
    "account": "ledger",
    "txn_type": "nikasi",
    "category": "TESTCASH",
    "party_type": "Truck",
    "description": "TEST_CashEntry_157aa17b - TestMandi - 9.9 Qntl @ Rs.2000",
    "amount": 200.0,
    "reference": "pvt_paddy_tdiesel:6788eb13",
    "kms_year": "2025-2026",
    "season": "Kharif",
    "created_by": "test",
    "linked_entry_id": "6788eb13-5a4b-4b58-b048-652a8ad76b31",
    "created_at": "2026-04-02T11:31:51.768724+00:00",
    "updated_at": "2026-04-02T11:31:51.768728+00:00"
  },
  {
    "_id": {
      "$oid": "69ce53a776786c5c90cf9254"
    },
    "id": "5ba2b974-4e4b-40d3-8064-1516fc46eaa5",
    "date": "2026-01-15",
    "account": "cash",
    "txn_type": "nikasi",
    "category": "TEST_CashEntry_157aa17b - TestMandi",
    "party_type": "Pvt Paddy Purchase",
    "description": "Advance - 9.9 Qntl @ Rs.2000",
    "amount": 1000.0,
    "reference": "pvt_paddy_adv:6788eb13",
    "kms_year": "2025-2026",
    "season": "Kharif",
    "created_by": "test",
    "linked_entry_id": "6788eb13-5a4b-4b58-b048-652a8ad76b31",
    "created_at": "2026-04-02T11:31:51.768724+00:00",
    "updated_at": "2026-04-02T11:31:51.768728+00:00"
  },
  {
    "_id": {
      "$oid": "69ce53a776786c5c90cf9255"
    },
    "id": "45f0fc51-7f06-4253-a216-1bb74f0be8b6",
    "date": "2026-01-15",
    "account": "ledger",
    "txn_type": "nikasi",
    "category": "TEST_CashEntry_157aa17b - TestMandi",
    "party_type": "Pvt Paddy Purchase",
    "description": "Advance - 9.9 Qntl @ Rs.2000",
    "amount": 1000.0,
    "reference": "pvt_paddy_advl:6788eb13",
    "kms_year": "2025-2026",
    "season": "Kharif",
    "created_by": "test",
    "linked_entry_id": "6788eb13-5a4b-4b58-b048-652a8ad76b31",
    "created_at": "2026-04-02T11:31:51.768724+00:00",
    "updated_at": "2026-04-02T11:31:51.768728+00:00"
  },
  {
    "_id": {
      "$oid": "69ce5786c42a97d1e42ec078"
    },
    "id": "5d90d710-46a2-42df-bbe4-43b652615b18",
    "date": "2026-04-02",
    "account": "cash",
    "txn_type": "nikasi",
    "category": "Test Party 162",
    "party_type": "Cash Party",
    "description": "Test transaction for iteration 162",
    "amount": 1000.0,
    "reference": "",
    "bank_name": "",
    "kms_year": "2025-2026",
    "season": "Kharif",
    "created_by": "",
    "created_at": "2026-04-02T11:48:22.118135+00:00",
    "updated_at": "2026-04-02T11:48:22.118147+00:00"
  },
  {
    "_id": {
      "$oid": "69ce5786c42a97d1e42ec079"
    },
    "id": "de9e64da-fe3e-4459-b9be-970979fa1891",
    "date": "2026-04-02",
    "account": "ledger",
    "txn_type": "nikasi",
    "category": "Test Party 162",
    "party_type": "Cash Party",
    "description": "Test transaction for iteration 162",
    "amount": 1000.0,
    "reference": "auto_ledger:5d90d710",
    "bank_name": "",
    "kms_year": "2025-2026",
    "season": "Kharif",
    "created_by": "",
    "created_at": "2026-04-02T11:48:22.125602+00:00",
    "updated_at": "2026-04-02T11:48:22.125612+00:00"
  },
  {
    "_id": {
      "$oid": "69ce5786c42a97d1e42ec07b"
    },
    "id": "8f846db4-71df-4276-a10a-d8133b922738",
    "date": "2026-04-02",
    "account": "ledger",
    "txn_type": "jama",
    "category": "Test Farmer 162 - Test Mandi",
    "party_type": "Pvt Paddy Purchase",
    "description": "Paddy Purchase: Test Farmer 162 - Test Mandi - 10.0Q @ Rs.2500.0/Q = Rs.25000.0",
    "amount": 25000.0,
    "bank_name": "",
    "reference": "pvt_party_jama:b8d7c14c",
    "kms_year": "2025-2026",
    "season": "Kharif",
    "created_by": "system",
    "linked_entry_id": "b8d7c14c-b4a9-4f3a-a155-b9aa05f5ed05",
    "created_at": "2026-04-02T11:48:22.339328+00:00",
    "updated_at": "2026-04-02T11:48:22.339330+00:00"
  },
  {
    "_id": {
      "$oid": "69ce57d50a99d14f2fe2a644"
    },
    "id": "c9fff793-a34a-4a0c-ba99-867345832caa",
    "date": "2026-04-02",
    "account": "cash",
    "txn_type": "nikasi",
    "category": "TEST_Party_162",
    "party_type": "Cash Party",
    "description": "Test transaction for iteration 162",
    "amount": 500.0,
    "reference": "",
    "bank_name": "",
    "kms_year": "2025-2026",
    "season": "Kharif",
    "created_by": "",
    "created_at": "2026-04-02T11:49:41.851220+00:00",
    "updated_at": "2026-04-02T11:49:41.851232+00:00"
  },
  {
    "_id": {
      "$oid": "69ce57d50a99d14f2fe2a645"
    },
    "id": "3e6ebc18-98de-4129-b677-9a3c99f30288",
    "date": "2026-04-02",
    "account": "ledger",
    "txn_type": "nikasi",
    "category": "TEST_Party_162",
    "party_type": "Cash Party",
    "description": "Test transaction for iteration 162",
    "amount": 500.0,
    "reference": "auto_ledger:c9fff793",
    "bank_name": "",
    "kms_year": "2025-2026",
    "season": "Kharif",
    "created_by": "",
    "created_at": "2026-04-02T11:49:41.858437+00:00",
    "updated_at": "2026-04-02T11:49:41.858446+00:00"
  },
  {
    "_id": {
      "$oid": "69ce57d60a99d14f2fe2a647"
    },
    "id": "4adb0f73-cfe4-4ef8-be4c-f894b3af41d7",
    "date": "2026-04-02",
    "account": "ledger",
    "txn_type": "jama",
    "category": "TEST_Farmer_162 - TestMandi",
    "party_type": "Pvt Paddy Purchase",
    "description": "Paddy Purchase: TEST_Farmer_162 - TestMandi - 5.0Q @ Rs.2000.0/Q = Rs.10000.0",
    "amount": 10000.0,
    "bank_name": "",
    "reference": "pvt_party_jama:a7eb410f",
    "kms_year": "2025-2026",
    "season": "Kharif",
    "created_by": "system",
    "linked_entry_id": "a7eb410f-a6bd-4594-9775-e0e7c5aeae01",
    "created_at": "2026-04-02T11:49:42.111174+00:00",
    "updated_at": "2026-04-02T11:49:42.111176+00:00"
  },
  {
    "_id": {
      "$oid": "69ceb268a4a981fef2f9b948"
    },
    "id": "4bfa220d-e2df-4092-a844-8d1985a1bf24",
    "date": "2025-01-15",
    "account": "cash",
    "txn_type": "jama",
    "category": "TEST_AUDIT_PARTY_158d07",
    "party_type": "Manual",
    "description": "Test cash transaction for audit",
    "amount": 5000.0,
    "reference": "",
    "bank_name": "",
    "kms_year": "2024-25",
    "season": "Kharif",
    "created_by": "admin",
    "created_at": "2026-04-02T18:16:08.648476+00:00",
    "updated_at": "2026-04-02T18:16:08.648492+00:00",
    "_v": 1
  },
  {
    "_id": {
      "$oid": "69ceb268a4a981fef2f9b94a"
    },
    "id": "4c739ae4-7d75-454b-b57c-f271e55bf18a",
    "date": "2025-01-15",
    "account": "ledger",
    "txn_type": "jama",
    "category": "TEST_AUDIT_PARTY_158d07",
    "party_type": "Manual",
    "description": "Test cash transaction for audit",
    "amount": 5000.0,
    "reference": "auto_ledger:4bfa220d",
    "bank_name": "",
    "kms_year": "2024-25",
    "season": "Kharif",
    "created_by": "admin",
    "created_at": "2026-04-02T18:16:08.649813+00:00",
    "updated_at": "2026-04-02T18:16:08.649816+00:00",
    "_v": 1
  },
  {
    "_id": {
      "$oid": "69ceb268a4a981fef2f9b94b"
    },
    "id": "22210683-3d80-4f1a-8df6-e2c60e1f713c",
    "date": "2025-01-15",
    "account": "cash",
    "txn_type": "jama",
    "category": "TEST_AUDIT_PARTY_578741",
    "party_type": "Manual",
    "description": "Updated cash transaction for audit test",
    "amount": 6000.0,
    "reference": "",
    "bank_name": "",
    "kms_year": "2024-25",
    "season": "Kharif",
    "created_by": "admin",
    "created_at": "2026-04-02T18:16:08.908973+00:00",
    "updated_at": "2026-04-02T18:16:09.122942+00:00",
    "_v": 2,
    "updated_by": "admin"
  },
  {
    "_id": {
      "$oid": "69ceb268a4a981fef2f9b94d"
    },
    "id": "ce7de21a-c53b-4cf9-b06d-8588a8f16d9d",
    "date": "2025-01-15",
    "account": "ledger",
    "txn_type": "jama",
    "category": "TEST_AUDIT_PARTY_578741",
    "party_type": "Manual",
    "description": "Updated cash transaction for audit test",
    "amount": 6000.0,
    "reference": "auto_ledger:22210683",
    "bank_name": "",
    "kms_year": "2024-25",
    "season": "Kharif",
    "created_by": "admin",
    "created_at": "2026-04-02T18:16:08.910390+00:00",
    "updated_at": "2026-04-02T18:16:09.122942+00:00",
    "_v": 1,
    "updated_by": "admin"
  },
  {
    "_id": {
      "$oid": "69ceb269a4a981fef2f9b956"
    },
    "id": "1dac5a31-743d-4df5-9f83-3a03344e1f5b",
    "date": "2025-01-15",
    "account": "ledger",
    "txn_type": "jama",
    "category": "TEST_AUDIT_PARTY_8c6f2b - Test Mandi",
    "party_type": "Pvt Paddy Purchase",
    "description": "Paddy Purchase: TEST_AUDIT_PARTY_8c6f2b - Test Mandi - 39.6Q @ Rs.2500.0/Q = Rs.99000.0",
    "amount": 99000.0,
    "bank_name": "",
    "reference": "pvt_party_jama:a0b3f011",
    "kms_year": "2024-25",
    "season": "Kharif",
    "created_by": "admin",
    "linked_entry_id": "a0b3f011-a623-4830-9faa-dc489175257f",
    "created_at": "2026-04-02T18:16:09.578143+00:00",
    "updated_at": "2026-04-02T18:16:09.578148+00:00"
  },
  {
    "_id": {
      "$oid": "69ceb269a4a981fef2f9b95d"
    },
    "id": "5d0fbfeb-afa2-44d7-8e58-84510626416f",
    "date": "2025-01-15",
    "account": "ledger",
    "txn_type": "jama",
    "category": "TEST_AUDIT_PARTY_50514b - Test Mandi",
    "party_type": "Pvt Paddy Purchase",
    "description": "Paddy Purchase: TEST_AUDIT_PARTY_50514b - Test Mandi - 44.6Q @ Rs.2500.0/Q = Rs.111500.0",
    "amount": 111500.0,
    "bank_name": "",
    "reference": "pvt_party_jama:ad586d2a",
    "kms_year": "2024-25",
    "season": "Kharif",
    "created_by": "admin",
    "linked_entry_id": "ad586d2a-d481-4d8c-b0e9-28cf4659d640",
    "created_at": "2026-04-02T18:16:09.918084+00:00",
    "updated_at": "2026-04-02T18:16:09.918089+00:00"
  },
  {
    "_id": {
      "$oid": "69ddfbe67edd03406d93a368"
    },
    "id": "16e94ec7-5b8e-46f0-a0ef-3345157ff0df",
    "date": "2026-04-13",
    "account": "ledger",
    "txn_type": "nikasi",
    "amount": 395488.8,
    "category": "Gayatri Agro",
    "party_type": "BP Sale",
    "description": "Rice Bran Sale #1",
    "reference": "bp_sale:2f89f1aa-18a",
    "kms_year": "2026-2027",
    "season": "Kharif",
    "created_by": "admin",
    "created_at": "2026-04-14T08:33:42.328184+00:00",
    "updated_at": "2026-04-14T08:33:42.328184+00:00"
  },
  {
    "_id": {
      "$oid": "69ddfbe67edd03406d93a369"
    },
    "id": "fb8b073c-7c50-4659-ae0d-28d1c4a8342e",
    "date": "2026-04-13",
    "account": "ledger",
    "txn_type": "jama",
    "amount": 1000.0,
    "category": "Jain",
    "party_type": "Diesel",
    "description": "Diesel for truck - Rice Bran #1 - Gayatri Agro",
    "reference": "bp_sale_diesel:2f89f1aa-18a",
    "kms_year": "2026-2027",
    "season": "Kharif",
    "created_by": "admin",
    "created_at": "2026-04-14T08:33:42.328184+00:00",
    "updated_at": "2026-04-14T08:33:42.328184+00:00"
  },
  {
    "_id": {
      "$oid": "69ddfbe67edd03406d93a36a"
    },
    "id": "13ad2257-3e7a-41d3-888d-7aa0d41436a2",
    "date": "2026-04-13",
    "account": "ledger",
    "txn_type": "nikasi",
    "amount": 1000.0,
    "category": "OD02AB1234",
    "party_type": "Truck",
    "description": "Truck diesel deduction - Rice Bran #1",
    "reference": "bp_truck_diesel:2f89f1aa-18a",
    "kms_year": "2026-2027",
    "season": "Kharif",
    "created_by": "admin",
    "created_at": "2026-04-14T08:33:42.328184+00:00",
    "updated_at": "2026-04-14T08:33:42.328184+00:00"
  },
  {
    "_id": {
      "$oid": "69ddfd6826b66acd1f530c27"
    },
    "id": "eac88057-1246-4176-9e41-2ca045e7e603",
    "date": "2026-04-14",
    "account": "cash",
    "txn_type": "nikasi",
    "category": "Tractor [Rakhad Fikai]",
    "party_type": "Rakhad",
    "description": "Cash payment to Tractor [Rakhad Fikai]",
    "amount": 1000.0,
    "reference": "",
    "bank_name": "",
    "kms_year": "2026-2027",
    "season": "Kharif",
    "created_by": "admin",
    "created_at": "2026-04-14T08:40:08.148877+00:00",
    "updated_at": "2026-04-14T08:40:08.148888+00:00",
    "_v": 1
  },
  {
    "_id": {
      "$oid": "69ddfd6826b66acd1f530c29"
    },
    "id": "e7382058-1177-4c21-a5e9-8151f06619db",
    "date": "2026-04-14",
    "account": "ledger",
    "txn_type": "nikasi",
    "category": "Tractor [Rakhad Fikai]",
    "party_type": "Rakhad",
    "description": "Cash payment to Tractor [Rakhad Fikai]",
    "amount": 1000.0,
    "reference": "auto_ledger:eac88057",
    "bank_name": "",
    "kms_year": "2026-2027",
    "season": "Kharif",
    "created_by": "admin",
    "created_at": "2026-04-14T08:40:08.150306+00:00",
    "updated_at": "2026-04-14T08:40:08.150312+00:00",
    "_v": 1
  },
  {
    "_id": {
      "$oid": "69e26a38f00efd95688679b6"
    },
    "id": "378f8c98-f392-4a25-bc06-ebf3e58a6c65",
    "date": "2026-02-15",
    "account": "cash",
    "txn_type": "nikasi",
    "category": "OD-15-A-1234 / OD-15-A-5678",
    "party_type": "Truck",
    "description": "DC Delivery Cash - TEST-TRUCK-MULTI | OD-15-A-1234 / OD-15-A-5678",
    "amount": 500,
    "reference": "delivery:e5eb858c",
    "bank_name": "",
    "linked_entry_id": "e5eb858c-27dc-4960-ab29-b68b3b09250d",
    "kms_year": "2025-2026",
    "season": "Kharif",
    "created_by": "admin",
    "created_at": "2026-04-17T17:13:28.864411+00:00",
    "updated_at": "2026-04-17T17:13:28.864411+00:00"
  },
  {
    "_id": {
      "$oid": "69e26a38f00efd95688679b7"
    },
    "id": "d33817f4-feaa-4a3d-8510-5dada19e197c",
    "date": "2026-02-15",
    "account": "ledger",
    "txn_type": "nikasi",
    "category": "OD-15-A-1234 / OD-15-A-5678",
    "party_type": "Truck",
    "description": "DC Delivery Cash - TEST-TRUCK-MULTI | OD-15-A-1234 / OD-15-A-5678",
    "amount": 500,
    "reference": "delivery_tcash:e5eb858c",
    "bank_name": "",
    "linked_entry_id": "e5eb858c-27dc-4960-ab29-b68b3b09250d",
    "kms_year": "2025-2026",
    "season": "Kharif",
    "created_by": "admin",
    "created_at": "2026-04-17T17:13:28.864411+00:00",
    "updated_at": "2026-04-17T17:13:28.864411+00:00"
  },
  {
    "_id": {
      "$oid": "69e26a38f00efd95688679b8"
    },
    "id": "ddb0abb3-02d5-4b3e-82e7-e0f6d5fefca9",
    "date": "2026-02-15",
    "account": "ledger",
    "txn_type": "nikasi",
    "category": "OD-15-A-1234 / OD-15-A-5678",
    "party_type": "Truck",
    "description": "DC Delivery Diesel - TEST-TRUCK-MULTI | OD-15-A-1234 / OD-15-A-5678",
    "amount": 2000,
    "reference": "delivery_tdiesel:e5eb858c",
    "bank_name": "",
    "linked_entry_id": "e5eb858c-27dc-4960-ab29-b68b3b09250d",
    "kms_year": "2025-2026",
    "season": "Kharif",
    "created_by": "admin",
    "created_at": "2026-04-17T17:13:28.864411+00:00",
    "updated_at": "2026-04-17T17:13:28.864411+00:00"
  },
  {
    "_id": {
      "$oid": "69e26a38f00efd95688679ba"
    },
    "id": "a6c9ef4a-eefa-4291-8b75-f395d6dbaae1",
    "date": "2026-02-15",
    "account": "ledger",
    "txn_type": "jama",
    "category": "Jain",
    "party_type": "Diesel",
    "description": "Diesel Fill: Truck OD-15-A-1234 / OD-15-A-5678 - Jain - Rs.2000.0",
    "amount": 2000,
    "reference": "delivery_dfill:e5eb858c",
    "bank_name": "",
    "linked_entry_id": "e5eb858c-27dc-4960-ab29-b68b3b09250d",
    "kms_year": "2025-2026",
    "season": "Kharif",
    "created_by": "admin",
    "created_at": "2026-04-17T17:13:28.864411+00:00",
    "updated_at": "2026-04-17T17:13:28.864411+00:00"
  },
  {
    "_id": {
      "$oid": "69ebc3f31a8812dde5bc7023"
    },
    "id": "27e2d072-5d8a-412f-aca6-9bcfb462ee79",
    "date": "2026-04-20",
    "account": "ledger",
    "txn_type": "jama",
    "amount": 925.0,
    "category": "Hemali Payment",
    "party_type": "Hemali",
    "description": "Vijay - Paddy Unload x100.0, Gummy Load x250.0 | Total: Rs.925",
    "reference": "hemali_work:889b8cc2-7d29-4607-86d8-ce6432f9028a",
    "kms_year": "2026-2027",
    "season": "Kharif",
    "created_by": "admin",
    "created_at": "2026-04-20T08:23:23.907838+00:00",
    "updated_at": "2026-04-24T19:26:43.795504+00:00"
  },
  {
    "_id": {
      "$oid": "69ebc3f31a8812dde5bc7024"
    },
    "id": "9c9c9fe9-1736-425c-917c-92f35db5148f",
    "date": "2026-02-15",
    "account": "ledger",
    "txn_type": "jama",
    "amount": 500.0,
    "category": "Hemali Payment",
    "party_type": "Hemali",
    "description": "Test Sardar - Loading x50.0 | Total: Rs.500",
    "reference": "hemali_work:0912b7d6-a3d5-43d4-b837-65f24aaf1168",
    "kms_year": "2025-2026",
    "season": "Kharif",
    "created_by": "",
    "created_at": "2026-04-24T19:03:12.301801+00:00",
    "updated_at": "2026-04-24T19:26:43.805723+00:00"
  },
  {
    "_id": {
      "$oid": "69ebc3f31a8812dde5bc7025"
    },
    "id": "ada898e2-b0cc-4d3b-8ea4-5f35dd0d5258",
    "date": "2026-03-10",
    "account": "ledger",
    "txn_type": "jama",
    "amount": 100.0,
    "category": "Hemali Payment",
    "party_type": "Hemali",
    "description": "Test Sardar 2 - Loading x20.0 | Total: Rs.100",
    "reference": "hemali_work:14d7e094-9c89-4211-b9c1-1e6f9b13879b",
    "kms_year": "2025-2026",
    "season": "Kharif",
    "created_by": "",
    "created_at": "2026-04-24T19:03:12.499351+00:00",
    "updated_at": "2026-04-24T19:26:43.806253+00:00"
  },
  {
    "_id": {
      "$oid": "69ec757b8695ae9a811458f2"
    },
    "id": "114fd4e9-e311-48ad-9ef3-6f3e449e375d",
    "date": "2026-04-25",
    "account": "ledger",
    "txn_type": "jama",
    "category": "OD-TEST-AGENT",
    "party_type": "Truck",
    "description": "Truck Entry: OD-TEST-AGENT - 290.4Q @ Rs.32",
    "amount": 9293,
    "reference": "truck_entry:965cd337",
    "kms_year": "2025-2026",
    "season": "Kharif",
    "created_by": "admin",
    "linked_entry_id": "965cd337-640f-4536-b9e7-bef5ab7b4c34",
    "created_at": "2026-04-25T08:04:11.060834+00:00",
    "updated_at": "2026-04-25T08:04:11.060839+00:00"
  },
  {
    "_id": {
      "$oid": "69ec87861e36a7e096afc7b6"
    },
    "reference": "agent_mandi:Kesinga|2025-2026|Kharif",
    "account": "ledger",
    "amount": 6761,
    "category": "Kesinga",
    "created_at": "2026-04-25T09:21:10.670901+00:00",
    "created_by": "system",
    "date": "2026-03-30",
    "description": "Agent Entry: Kesinga - 676.07Q \u00d7 Rs.10.0 = Rs.6761 (2 entries)",
    "id": "c3ca2e0f-746d-4452-969e-ed0dabb7f5e5",
    "kms_year": "2025-2026",
    "linked_target_id": "9e027fcb-d090-465d-ba69-b0d9a5f1edfb",
    "party_type": "Agent",
    "season": "Kharif",
    "txn_type": "jama",
    "updated_at": "2026-05-03T08:01:53.246789+00:00"
  },
  {
    "_id": {
      "$oid": "69f0ba0769eeb942ce6cd221"
    },
    "id": "3c505306-6879-47d7-bc3f-40c5298a27d4",
    "date": "2026-04-28",
    "account": "cash",
    "txn_type": "jama",
    "category": "Titu",
    "party_type": "Owner",
    "description": "Cash received from Titu",
    "amount": 50000.0,
    "reference": "",
    "bank_name": "",
    "owner_name": "",
    "kms_year": "2025-2026",
    "season": "Kharif",
    "created_by": "admin",
    "created_at": "2026-04-28T13:45:43.274725+00:00",
    "updated_at": "2026-04-28T13:45:43.274737+00:00",
    "_v": 1
  },
  {
    "_id": {
      "$oid": "69f0ba0769eeb942ce6cd223"
    },
    "id": "b71cbece-ca05-4042-ac90-7a7a7772b512",
    "date": "2026-04-28",
    "account": "ledger",
    "txn_type": "jama",
    "category": "Titu",
    "party_type": "Owner",
    "description": "Cash received from Titu",
    "amount": 50000.0,
    "reference": "auto_ledger:3c505306",
    "bank_name": "",
    "owner_name": "",
    "kms_year": "2025-2026",
    "season": "Kharif",
    "created_by": "admin",
    "created_at": "2026-04-28T13:45:43.276113+00:00",
    "updated_at": "2026-04-28T13:45:43.276116+00:00",
    "_v": 1
  },
  {
    "_id": {
      "$oid": "69f0ba3669eeb942ce6cd224"
    },
    "id": "485d12a0-0de0-4763-a3ba-020fea8e1cdf",
    "date": "2026-04-28",
    "account": "owner",
    "txn_type": "nikasi",
    "category": "CtrlSTestParty",
    "party_type": "Cash Party",
    "description": "Owner payment to CtrlSTestParty",
    "amount": 10000.0,
    "reference": "",
    "bank_name": "",
    "owner_name": "Titu",
    "kms_year": "2025-2026",
    "season": "Kharif",
    "created_by": "admin",
    "created_at": "2026-04-28T13:46:30.378749+00:00",
    "updated_at": "2026-04-28T13:46:30.378759+00:00",
    "_v": 1
  },
  {
    "_id": {
      "$oid": "69f0bc4b8d72d6b0cc8839f5"
    },
    "id": "758fc697-271e-4ad1-a8d0-e3a091842cdd",
    "date": "2026-04-28",
    "account": "owner",
    "txn_type": "nikasi",
    "category": "CtrlSTestParty",
    "party_type": "Cash Party",
    "description": "Owner payment to CtrlSTestParty",
    "amount": 5000.0,
    "reference": "",
    "bank_name": "",
    "owner_name": "Titu",
    "kms_year": "2025-2026",
    "season": "Kharif",
    "created_by": "admin",
    "created_at": "2026-04-28T13:55:23.228783+00:00",
    "updated_at": "2026-04-28T13:55:23.228794+00:00",
    "_v": 1
  },
  {
    "_id": {
      "$oid": "69f0c1915ec213874a4a1c54"
    },
    "id": "be16c2a4-bfd7-436e-b238-6b2a95245a83",
    "date": "2026-04-28",
    "account": "owner",
    "txn_type": "nikasi",
    "category": "DieselTest",
    "party_type": "Diesel",
    "description": "Titu paid diesel",
    "amount": 1500.0,
    "reference": "",
    "bank_name": "",
    "owner_name": "Titu",
    "kms_year": "2025-2026",
    "season": "Kharif",
    "created_by": "admin",
    "created_at": "2026-04-28T14:17:53.301059+00:00",
    "updated_at": "2026-04-28T14:17:53.301068+00:00",
    "_v": 1
  },
  {
    "_id": {
      "$oid": "69f23561dd4bcc66c0072e2f"
    },
    "id": "3fa9319f-b344-4742-97e5-062d2c5653ff",
    "date": "2026-04-29",
    "account": "ledger",
    "txn_type": "nikasi",
    "amount": 325500.0,
    "category": "Cash Test Agent (PKA)",
    "party_type": "BP Sale",
    "description": "Rice Bran Sale #e5bf489e - Pakka (GST Bill)",
    "reference": "bp_sale_pka:e5bf489e-10b",
    "kms_year": "2026-2027",
    "season": "Kharif",
    "created_by": "system",
    "created_at": "2026-04-29T16:44:17.614042+00:00",
    "updated_at": "2026-04-29T16:44:17.614042+00:00"
  },
  {
    "_id": {
      "$oid": "69f23561dd4bcc66c0072e30"
    },
    "id": "660bfd16-8ad8-4bf0-9065-8b0767fb33fc",
    "date": "2026-04-29",
    "account": "ledger",
    "txn_type": "nikasi",
    "amount": 295963.0,
    "category": "Cash Test Agent (KCA)",
    "party_type": "BP Sale",
    "description": "Rice Bran Sale #e5bf489e - Kaccha (Slip)",
    "reference": "bp_sale_ka:e5bf489e-10b",
    "kms_year": "2026-2027",
    "season": "Kharif",
    "created_by": "system",
    "created_at": "2026-04-29T16:44:17.614042+00:00",
    "updated_at": "2026-04-29T16:44:17.614042+00:00"
  },
  {
    "_id": {
      "$oid": "69f23f6308d489f10068bd95"
    },
    "id": "6d988e3a-8778-4213-a87c-fa1e14a97986",
    "date": "2026-04-29",
    "account": "bank",
    "txn_type": "jama",
    "category": "MBOPL (PKA)",
    "party_type": "BP Sale",
    "description": "Bank received from MBOPL (PKA)",
    "amount": 315000.0,
    "reference": "",
    "bank_name": "",
    "owner_name": "",
    "kms_year": "2026-2027",
    "season": "Kharif",
    "created_by": "admin",
    "created_at": "2026-04-29T17:26:59.827653+00:00",
    "updated_at": "2026-04-29T17:26:59.827663+00:00",
    "_v": 1
  },
  {
    "_id": {
      "$oid": "69f23f6308d489f10068bd97"
    },
    "id": "f0807d7d-3b64-4c50-9707-596161f987a8",
    "date": "2026-04-29",
    "account": "ledger",
    "txn_type": "jama",
    "category": "MBOPL (PKA)",
    "party_type": "BP Sale",
    "description": "Bank received from MBOPL (PKA)",
    "amount": 315000.0,
    "reference": "auto_ledger:6d988e3a",
    "bank_name": "",
    "owner_name": "",
    "kms_year": "2026-2027",
    "season": "Kharif",
    "created_by": "admin",
    "created_at": "2026-04-29T17:26:59.832803+00:00",
    "updated_at": "2026-04-29T17:26:59.832806+00:00",
    "_v": 1
  },
  {
    "_id": {
      "$oid": "69f23fa6f85f6ddc3182953f"
    },
    "id": "9eade602-5fcb-4256-8948-7dd86733a49e",
    "date": "2026-04-13",
    "account": "ledger",
    "txn_type": "nikasi",
    "amount": 8437.09,
    "category": "Gayatri Agro (KCA)",
    "party_type": "BP Sale",
    "description": "Lab Test Bonus (+0.56%) - Voucher #1",
    "reference": "oil_premium:b7e020ec-922",
    "kms_year": "2026-2027",
    "season": "Kharif",
    "created_by": "system",
    "created_at": "2026-04-29T17:28:06.007770+00:00",
    "updated_at": "2026-04-29T17:28:06.007770+00:00"
  },
  {
    "_id": {
      "$oid": "69f23fa6f85f6ddc31829541"
    },
    "id": "0e4ef1f2-b2c2-4ec9-93e9-079b280a573e",
    "date": "2026-04-29",
    "account": "ledger",
    "txn_type": "jama",
    "amount": 76086.68,
    "category": "Cash Test Agent (KCA)",
    "party_type": "BP Sale",
    "description": "Lab Test Premium (-3.0%) - Voucher #2",
    "reference": "oil_premium:fa0b65e2-3aa",
    "kms_year": "2026-2027",
    "season": "Kharif",
    "created_by": "system",
    "created_at": "2026-04-29T17:28:06.008980+00:00",
    "updated_at": "2026-04-29T17:28:06.008980+00:00"
  },
  {
    "_id": {
      "$oid": "69f23fa6f85f6ddc31829543"
    },
    "id": "730d6eea-66a7-4b4c-b8f0-8f91a45b0f74",
    "date": "2026-04-29",
    "account": "ledger",
    "txn_type": "jama",
    "amount": 77195.45,
    "category": "MBOPL (KCA)",
    "party_type": "BP Sale",
    "description": "Lab Test Premium (-3.06%) - Voucher #7",
    "reference": "oil_premium:8739ab1f-437",
    "kms_year": "2026-2027",
    "season": "Kharif",
    "created_by": "system",
    "created_at": "2026-04-29T17:28:06.010024+00:00",
    "updated_at": "2026-04-29T17:28:06.010024+00:00"
  },
  {
    "_id": {
      "$oid": "69f24b95c25ad35813c2bc9b"
    },
    "id": "915a0071-9b30-4498-a1fa-93857b7b39ed",
    "date": "2026-04-29",
    "account": "cash",
    "txn_type": "jama",
    "category": "Titu",
    "party_type": "Owner",
    "description": "Cash received from Titu",
    "amount": 100000.0,
    "reference": "",
    "bank_name": "",
    "owner_name": "",
    "kms_year": "2026-2027",
    "season": "Kharif",
    "created_by": "admin",
    "created_at": "2026-04-29T18:19:01.421733+00:00",
    "updated_at": "2026-04-29T18:19:01.421752+00:00",
    "_v": 1
  },
  {
    "_id": {
      "$oid": "69f24b95c25ad35813c2bc9d"
    },
    "id": "64a11db9-7bf7-42b8-985e-e37898cc14fd",
    "date": "2026-04-29",
    "account": "ledger",
    "txn_type": "jama",
    "category": "Titu",
    "party_type": "Owner",
    "description": "Cash received from Titu",
    "amount": 100000.0,
    "reference": "auto_ledger:915a0071",
    "bank_name": "",
    "owner_name": "",
    "kms_year": "2026-2027",
    "season": "Kharif",
    "created_by": "admin",
    "created_at": "2026-04-29T18:19:01.423069+00:00",
    "updated_at": "2026-04-29T18:19:01.423072+00:00",
    "_v": 1
  },
  {
    "_id": {
      "$oid": "69f24bcac25ad35813c2bc9e"
    },
    "id": "74321007-f36e-4218-a97a-6c5e926b57db",
    "date": "2026-04-29",
    "account": "owner",
    "txn_type": "nikasi",
    "category": "Tractor [Rakhad Fikai]",
    "party_type": "Rakhad",
    "description": "Owner payment to Tractor [Rakhad Fikai]",
    "amount": 1000.0,
    "reference": "",
    "bank_name": "",
    "owner_name": "Titu",
    "kms_year": "2026-2027",
    "season": "Kharif",
    "created_by": "admin",
    "created_at": "2026-04-29T18:19:54.075779+00:00",
    "updated_at": "2026-04-29T18:19:54.075790+00:00",
    "_v": 1
  },
  {
    "_id": {
      "$oid": "69f24fccc25ad35813c2bca1"
    },
    "id": "f8a03289-5c67-44dc-9d9a-b6e73be6d072",
    "date": "2026-02-15",
    "account": "owner",
    "txn_type": "nikasi",
    "category": "Rakhad Fikai Test",
    "party_type": "Cash Party",
    "description": "Test: Titu paid Rakhad Fikai",
    "amount": 1000.0,
    "reference": "",
    "bank_name": "",
    "owner_name": "Titu",
    "kms_year": "2025-2026",
    "season": "Kharif",
    "created_by": "admin",
    "created_at": "2026-04-29T18:37:00.950928+00:00",
    "updated_at": "2026-04-29T18:37:00.950938+00:00",
    "_v": 1
  },
  {
    "_id": {
      "$oid": "69f2548b039d31a466399a27"
    },
    "id": "3f09ad6f-89b7-44d4-b552-622a613412a6",
    "date": "2026-04-29",
    "account": "cash",
    "txn_type": "jama",
    "category": "Titu",
    "party_type": "Owner",
    "description": "Cash received from Titu",
    "amount": 50000.0,
    "reference": "",
    "bank_name": "",
    "owner_name": "",
    "kms_year": "2026-2027",
    "season": "Kharif",
    "created_by": "admin",
    "created_at": "2026-04-29T18:57:15.032888+00:00",
    "updated_at": "2026-04-29T18:57:15.032898+00:00",
    "_v": 1
  },
  {
    "_id": {
      "$oid": "69f2548b039d31a466399a29"
    },
    "id": "37a51d53-af84-42b8-93b3-744271245703",
    "date": "2026-04-29",
    "account": "ledger",
    "txn_type": "jama",
    "category": "Titu",
    "party_type": "Owner",
    "description": "Cash received from Titu",
    "amount": 50000.0,
    "reference": "auto_ledger:3f09ad6f",
    "bank_name": "",
    "owner_name": "",
    "kms_year": "2026-2027",
    "season": "Kharif",
    "created_by": "admin",
    "created_at": "2026-04-29T18:57:15.034166+00:00",
    "updated_at": "2026-04-29T18:57:15.034168+00:00",
    "_v": 1
  },
  {
    "_id": {
      "$oid": "69f254d9d6efb40b6978474f"
    },
    "id": "ae1b8570-98f2-412b-95b4-402bf60919d9",
    "date": "2026-04-29",
    "account": "cash",
    "txn_type": "nikasi",
    "category": "Titu",
    "party_type": "Owner",
    "description": "Cash payment to Titu",
    "amount": 100000.0,
    "reference": "",
    "bank_name": "",
    "owner_name": "",
    "kms_year": "2026-2027",
    "season": "Kharif",
    "created_by": "admin",
    "created_at": "2026-04-29T18:58:33.639482+00:00",
    "updated_at": "2026-04-29T18:58:33.639491+00:00",
    "_v": 1
  },
  {
    "_id": {
      "$oid": "69f254d9d6efb40b69784751"
    },
    "id": "14067181-3cb5-4fd5-9709-04586a202adc",
    "date": "2026-04-29",
    "account": "ledger",
    "txn_type": "nikasi",
    "category": "Titu",
    "party_type": "Owner",
    "description": "Cash payment to Titu",
    "amount": 100000.0,
    "reference": "auto_ledger:ae1b8570",
    "bank_name": "",
    "owner_name": "",
    "kms_year": "2026-2027",
    "season": "Kharif",
    "created_by": "admin",
    "created_at": "2026-04-29T18:58:33.640635+00:00",
    "updated_at": "2026-04-29T18:58:33.640637+00:00",
    "_v": 1
  },
  {
    "_id": {
      "$oid": "69f2561df3d04050a75fbd8e"
    },
    "id": "89bfbecb-f9ad-4b3e-8a91-ea4534222131",
    "date": "2026-04-29",
    "account": "owner",
    "txn_type": "nikasi",
    "category": "Trahikara",
    "party_type": "Thikadar",
    "description": "Building",
    "amount": 27000.0,
    "reference": "",
    "bank_name": "",
    "owner_name": "Titu",
    "kms_year": "2026-2027",
    "season": "Kharif",
    "created_by": "admin",
    "created_at": "2026-04-29T19:03:57.332253+00:00",
    "updated_at": "2026-04-29T19:03:57.332263+00:00",
    "_v": 1
  },
  {
    "_id": {
      "$oid": "69f34b4f2a0deb5a2ba76c33"
    },
    "date": "2025-01-15",
    "account": "ledger",
    "txn_type": "jama",
    "category": "TEST_BHADA_OD04GH3456",
    "party_type": "Truck",
    "amount": 2000.0,
    "description": "Purchase Bhada (RST #1) \u2192 TEST_BHADA_Delete Cascade Test",
    "kms_year": "2024-2025",
    "season": "Kharif",
    "created_by": "admin",
    "linked_entry_id": "817e2f9c-cc29-4190-807a-4927c6e43158",
    "reference": "vw_purchase_bhada:1",
    "updated_at": "2026-04-30T12:30:07.327940+00:00",
    "id": "ba7db1cc-ddca-4926-ad4c-f7a3bf12f5be",
    "created_at": "2026-04-30T12:30:07.327940+00:00"
  },
  {
    "_id": {
      "$oid": "69f3788eb5631d0525820b9b"
    },
    "id": "e64bf8e1-303d-4431-b1c6-70199becf96c",
    "date": "2026-04-29",
    "account": "ledger",
    "txn_type": "nikasi",
    "amount": 315000.0,
    "category": "MBOPL (PKA)",
    "party_type": "BP Sale",
    "description": "Rice Bran Sale #e22f4323 - Pakka (GST Bill)",
    "reference": "bp_sale_pka:e22f4323-dfe",
    "kms_year": "2026-2027",
    "season": "Kharif",
    "created_by": "admin",
    "created_at": "2026-04-30T15:43:10.212176+00:00",
    "updated_at": "2026-04-30T15:43:10.212176+00:00"
  },
  {
    "_id": {
      "$oid": "69f3788eb5631d0525820b9c"
    },
    "id": "b30facd8-2c77-4679-976b-2caa36281d5b",
    "date": "2026-04-29",
    "account": "ledger",
    "txn_type": "nikasi",
    "amount": 185000.0,
    "category": "MBOPL (KCA)",
    "party_type": "BP Sale",
    "description": "Rice Bran Sale #e22f4323 - Kaccha (Slip)",
    "reference": "bp_sale_ka:e22f4323-dfe",
    "kms_year": "2026-2027",
    "season": "Kharif",
    "created_by": "admin",
    "created_at": "2026-04-30T15:43:10.212176+00:00",
    "updated_at": "2026-04-30T15:43:10.212176+00:00"
  },
  {
    "_id": {
      "$oid": "69f3788fb5631d0525820b9f"
    },
    "date": "2026-04-29",
    "account": "ledger",
    "txn_type": "jama",
    "category": "MH-12-AB-1234",
    "party_type": "Truck",
    "amount": 4500.0,
    "description": "Sale Bhada (RST #7) \u2192 Amath",
    "kms_year": "2026-2027",
    "season": "Kharif",
    "created_by": "admin",
    "linked_entry_id": "ee0b99a8-d051-4cb1-b09e-b0d5f5cce1f4",
    "reference": "vw_sale_bhada:7",
    "updated_at": "2026-05-02T18:29:39.481962+00:00",
    "id": "e8604cb0-8d6b-4446-9e40-9e93136371a9",
    "created_at": "2026-04-30T15:43:11.142906+00:00"
  },
  {
    "_id": {
      "$oid": "69f38ca7f51e284688bd6246"
    },
    "id": "a1f39130-eedb-48f3-aac9-bb4fdcfa5008",
    "date": "2026-04-30",
    "account": "cash",
    "txn_type": "nikasi",
    "category": "TESTKG01",
    "party_type": "Truck",
    "description": "Truck Payment: TESTKG01 (Full - Mark Paid)",
    "amount": 250,
    "reference": "truck_markpaid:08b9362c-d04e-4e99-a1d9-cc33e6ee03b3",
    "kms_year": "2026-2027",
    "season": "Kharif",
    "created_by": "admin",
    "linked_payment_id": "truck:08b9362c-d04e-4e99-a1d9-cc33e6ee03b3",
    "created_at": "2026-04-30T17:08:55.675443+00:00",
    "updated_at": "2026-04-30T17:08:55.675445+00:00"
  },
  {
    "_id": {
      "$oid": "69f38ca7f51e284688bd6247"
    },
    "id": "0abffa1d-b349-439b-ac6e-e17c0b910a7a",
    "date": "2026-04-30",
    "account": "ledger",
    "txn_type": "nikasi",
    "category": "TESTKG01",
    "party_type": "Truck",
    "description": "Truck Payment: TESTKG01 (Full - Mark Paid)",
    "amount": 250,
    "reference": "truck_markpaid_ledger:08b9362c-d04e-4e99-a1d9-cc33e6ee03b3",
    "kms_year": "2026-2027",
    "season": "Kharif",
    "created_by": "admin",
    "linked_payment_id": "truck_ledger_markpaid:08b9362c-d04e-4e99-a1d9-cc33e6ee03b3",
    "created_at": "2026-04-30T17:08:55.676012+00:00",
    "updated_at": "2026-04-30T17:08:55.676015+00:00"
  },
  {
    "_id": {
      "$oid": "69f6ec743f9e209753955547"
    },
    "id": "3573160a-fd76-4695-abd4-3581d5379d0e",
    "date": "2026-05-03",
    "account": "ledger",
    "txn_type": "nikasi",
    "amount": 315000.0,
    "category": "MBOPL (PKA)",
    "party_type": "BP Sale",
    "description": "Rice Bran Sale #S-006 - Pakka (GST Bill)",
    "reference": "bp_sale_pka:a16a2969-965",
    "kms_year": "2026-2027",
    "season": "Kharif",
    "created_by": "admin",
    "created_at": "2026-05-03T06:34:28.528996+00:00",
    "updated_at": "2026-05-03T06:34:28.528996+00:00"
  },
  {
    "_id": {
      "$oid": "69f6ec743f9e209753955548"
    },
    "id": "366fd2ee-cd58-4253-ad23-538c91e3cc79",
    "date": "2026-05-03",
    "account": "ledger",
    "txn_type": "nikasi",
    "amount": 185000.0,
    "category": "MBOPL (KCA)",
    "party_type": "BP Sale",
    "description": "Rice Bran Sale #S-006 - Kaccha (Slip)",
    "reference": "bp_sale_ka:a16a2969-965",
    "kms_year": "2026-2027",
    "season": "Kharif",
    "created_by": "admin",
    "created_at": "2026-05-03T06:34:28.528996+00:00",
    "updated_at": "2026-05-03T06:34:28.528996+00:00"
  }
]